Workbook

Sheet Actual
A1: Player | B1: Roster Position | C1: %Drafted | D1: FPTS
A2: Nathan MacKinnon | B2: C | C2: 0.2846 | D2: 11.5
A3: Victor Olofsson | B3: W | C3: 0.2487 | D3: 14.3
A4: Will Smith | B4: W | C4: 0.2414 | D4: 13
A5: Macklin Celebrini | B5: C | C5: 0.2361 | D5: 23
A6: Dougie Hamilton | B6: D | C6: 0.1772 | D6: 7.8
A7: Jared McCann | B7: W | C7: 0.1536 | D7: 13
A8: Matty Beniers | B8: C | C8: 0.1514 | D8: 7.8
A9: Martin Necas | B9: UTIL | C9: 0.1508 | D9: 26.5
A10: Philipp Grubauer | B10: G | C10: 0.1433 | D10: 8.4
A11: Nikita Kucherov | B11: W | C11: 0.1427 | D11: 11.5
A12: Logan Thompson | B12: G | C12: 0.1248 | D12: 20
A13: Brandon Hagel | B13: W | C13: 0.1222 | D13: 8
... A303: Ian Moore | B303: W | C303: 0.0003 | D303: 9.8

Sheet Projection
A1: name | B1: team | C1: position | D1: dk_pos | E1: salary | F1: projected_fpts | G1: floor | H1: ceiling | I1: dk_avg_fpts | J1: edge | K1: value | L1: goals_per_game | M1: assists_per_game | N1: shots_per_game | O1: pp_points_per_game | P1: projection_date | Q1: timestamp | R1: actual | S1: ownership | T1: TOI
A2: Freddy Gaudreau | B2: SEA | C2: C | D2: RW | E2: 2900 | F2: 5.8025683 | G2: 2.3210273 | H2: 19.506421 | I2: 5.15 | J2: 0.65256828 | K2: 2.0008856 | L2: 0.11111111 | M2: 0.25 | N2: 1.0555556 | O2: 0.055555556 | P2: 2026-01-23 | Q2: 20260123_190750 | R2: =IFERROR(VLOOKUP($A2,Actual!$A:$D,4,FALSE),IFERROR(VLOOKUP($A2,FC!$A:$AC,29,FALSE), "Not Found")) -> 1.5 | S2: =IFERROR(VLOOKUP($A2,Actual!$A:$D,3,FALSE),"0") -> 0.0006 | T2: =VLOOKUP(A2,NHT!B:F,5,FALSE) -> 13.416667
A3: Martin Fehervary | B3: WSH | C3: D | D3: D | E3: 3300 | F3: 6.8597419 | G3: 2.7438967 | H3: 22.149355 | I3: 7.14 | J3: -0.28025813 | K3: 2.0787097 | L3: 0.058823529 | M3: 0.2745098 | N3: 1.0588235 | O3: 0 | P3: 2026-01-23 | Q3: 20260123_190750 | R3: =IFERROR(VLOOKUP($A3,Actual!$A:$D,4,FALSE),IFERROR(VLOOKUP($A3,FC!$A:$AC,29,FALSE), "Not Found")) -> 14.3 | S3: =IFERROR(VLOOKUP($A3,Actual!$A:$D,3,FALSE),"0") -> 0.0048 | T3: =VLOOKUP(A3,NHT!B:F,5,FALSE) -> 18.983333
A4: Arvid Soderblom | B4: CHI | C4: G | D4: G | E4: 7000 | F4: 8.4987664 | G4: 2.5496299 | H4: 26.997533 | I4: 6.69 | J4: 1.8087664 | K4: 1.2141095 | P4: 2026-01-23 | Q4: 20260123_190750 | R4: =IFERROR(VLOOKUP($A4,Actual!$A:$D,4,FALSE),IFERROR(VLOOKUP($A4,FC!$A:$AC,29,FALSE), "Not Found")) -> 19.5 | S4: =IFERROR(VLOOKUP($A4,Actual!$A:$D,3,FALSE),"0") -> 0.021 | T4: =VLOOKUP(A4,NHT!B:F,5,FALSE) -> 65
A5: Andrei Vasilevskiy | B5: TBL | C5: G | D5: G | E5: 8400 | F5: 14.900869 | G5: 4.4702607 | H5: 39.801738 | I5: 13.4 | J5: 1.5008691 | K5: 1.773913 | P5: 2026-01-23 | Q5: 20260123_190750 | R5: =IFERROR(VLOOKUP($A5,Actual!$A:$D,4,FALSE),IFERROR(VLOOKUP($A5,FC!$A:$AC,29,FALSE), "Not Found")) -> 14.4 | S5: =IFERROR(VLOOKUP($A5,Actual!$A:$D,3,FALSE),"0") -> 0.0877 | T5: =VLOOKUP(A5,NHT!B:F,5,FALSE) -> 65
A6: Alex Nedeljkovic | B6: SJS | C6: G | D6: G | E6: 8000 | F6: 14.092368 | G6: 4.2277105 | H6: 38.184737 | I6: 10.26 | J6: 3.8323685 | K6: 1.7615461 | P6: 2026-01-23 | Q6: 20260123_190750 | R6: =IFERROR(VLOOKUP($A6,Actual!$A:$D,4,FALSE),IFERROR(VLOOKUP($A6,FC!$A:$AC,29,FALSE), "Not Found")) -> 22.1 | S6: =IFERROR(VLOOKUP($A6,Actual!$A:$D,3,FALSE),"0") -> 0.0502 | T6: =VLOOKUP(A6,NHT!B:F,5,FALSE) -> 60
A7: Lukas Dostal | B7: ANA | C7: G | D7: G | E7: 7600 | F7: 12.135659 | G7: 3.6406977 | H7: 34.271318 | I7: 10.22 | J7: 1.915659 | K7: 1.5967972 | P7: 2026-01-23 | Q7: 20260123_190750 | R7: =IFERROR(VLOOKUP($A7,Actual!$A:$D,4,FALSE),IFERROR(VLOOKUP($A7,FC!$A:$AC,29,FALSE), "Not Found")) -> 13 | S7: =IFERROR(VLOOKUP($A7,Actual!$A:$D,3,FALSE),"0") -> 0.0589 | T7: =VLOOKUP(A7,NHT!B:F,5,FALSE) -> 60
A8: Adin Hill | B8: VGK | C8: G | D8: G | E8: 7900 | F8: 6.7077291 | G8: 2.0123187 | H8: 23.415458 | I8: 5.49 | J8: 1.2177291 | K8: 0.84907963 | P8: 2026-01-23 | Q8: 20260123_190750 | R8: =IFERROR(VLOOKUP($A8,Actual!$A:$D,4,FALSE),IFERROR(VLOOKUP($A8,FC!$A:$AC,29,FALSE), "Not Found")) -> 8.1 | S8: =IFERROR(VLOOKUP($A8,Actual!$A:$D,3,FALSE),"0") -> 0.0084 | T8: =VLOOKUP(A8,NHT!B:F,5,FALSE) -> 60
A9: Jacob Markstrom | B9: NJD | C9: G | D9: G | E9: 8100 | F9: 10.52228 | G9: 3.1566841 | H9: 31.044561 | I9: 9.07 | J9: 1.4522803 | K9: 1.2990469 | P9: 2026-01-23 | Q9: 20260123_190750 | R9: =IFERROR(VLOOKUP($A9,Actual!$A:$D,4,FALSE),IFERROR(VLOOKUP($A9,FC!$A:$AC,29,FALSE), "Not Found")) -> 6.7 | S9: =IFERROR(VLOOKUP($A9,Actual!$A:$D,3,FALSE),"0") -> 0.0505 | T9: =VLOOKUP(A9,NHT!B:F,5,FALSE) -> 60
A10: Samuel Ersson | B10: PHI | C10: G | D10: G | E10: 7100 | F10: 6.4049538 | G10: 1.9214862 | H10: 22.809908 | I10: 4.95 | J10: 1.4549538 | K10: 0.90210618 | P10: 2026-01-23 | Q10: 20260123_190750 | R10: =IFERROR(VLOOKUP($A10,Actual!$A:$D,4,FALSE),IFERROR(VLOOKUP($A10,FC!$A:$AC,29,FALSE), "Not Found")) -> 17.9 | S10: =IFERROR(VLOOKUP($A10,Actual!$A:$D,3,FALSE),"0") -> 0.0179 | T10: =VLOOKUP(A10,NHT!B:F,5,FALSE) -> 59.9
A11: Logan Thompson | B11: WSH | C11: G | D11: G | E11: 7800 | F11: 14.06135 | G11: 4.2184049 | H11: 38.122699 | I11: 12.91 | J11: 1.1513497 | K11: 1.8027371 | P11: 2026-01-23 | Q11: 20260123_190750 | R11: =IFERROR(VLOOKUP($A11,Actual!$A:$D,4,FALSE),IFERROR(VLOOKUP($A11,FC!$A:$AC,29,FALSE), "Not Found")) -> 20 | S11: =IFERROR(VLOOKUP($A11,Actual!$A:$D,3,FALSE),"0") -> 0.1248 | T11: =VLOOKUP(A11,NHT!B:F,5,FALSE) -> 59.866667
A12: Jake Oettinger | B12: DAL | C12: G | D12: G | E12: 8200 | F12: 13.623843 | G12: 4.0871529 | H12: 37.247686 | I12: 11.92 | J12: 1.7038429 | K12: 1.6614443 | P12: 2026-01-23 | Q12: 20260123_190750 | R12: =IFERROR(VLOOKUP($A12,Actual!$A:$D,4,FALSE),IFERROR(VLOOKUP($A12,FC!$A:$AC,29,FALSE), "Not Found")) -> 13 | S12: =IFERROR(VLOOKUP($A12,Actual!$A:$D,3,FALSE),"0") -> 0.0622 | T12: =VLOOKUP(A12,NHT!B:F,5,FALSE) -> 59.8
A13: Jordan Binnington | B13: STL | C13: G | D13: G | E13: 7200 | F13: 7.5891931 | G13: 2.2767579 | H13: 25.178386 | I13: 6.4 | J13: 1.1891931 | K13: 1.0540546 | P13: 2026-01-23 | Q13: 20260123_190750 | R13: =IFERROR(VLOOKUP($A13,Actual!$A:$D,4,FALSE),IFERROR(VLOOKUP($A13,FC!$A:$AC,29,FALSE), "Not Found")) -> 0.7 | S13: =IFERROR(VLOOKUP($A13,Actual!$A:$D,3,FALSE),"0") -> 0.032 | T13: =VLOOKUP(A13,NHT!B:F,5,FALSE) -> 59
A14: Philipp Grubauer | B14: SEA | C14: G | D14: G | E14: 7800 | F14: 17.544782 | G14: 5.2634347 | H14: 45.089565 | I14: 13.82 | J14: 3.7247825 | K14: 2.2493311 | P14: 2026-01-23 | Q14: 20260123_190750 | R14: =IFERROR(VLOOKUP($A14,Actual!$A:$D,4,FALSE),IFERROR(VLOOKUP($A14,FC!$A:$AC,29,FALSE), "Not Found")) -> 8.4 | S14: =IFERROR(VLOOKUP($A14,Actual!$A:$D,3,FALSE),"0") -> 0.1433 | T14: =VLOOKUP(A14,NHT!B:F,5,FALSE) -> 58.683333
A15: Devin Cooley | B15: CGY | C15: G | D15: G | E15: 7600 | F15: 16.854585 | G15: 5.0563756 | H15: 43.709171 | I15: 12.58 | J15: 4.2745854 | K15: 2.2177086 | P15: 2026-01-23 | Q15: 20260123_190750 | R15: =IFERROR(VLOOKUP($A15,Actual!$A:$D,4,FALSE),IFERROR(VLOOKUP($A15,FC!$A:$AC,29,FALSE), "Not Found")) -> 20.5 | S15: =IFERROR(VLOOKUP($A15,Actual!$A:$D,3,FALSE),"0") -> 0.0771 | T15: =VLOOKUP(A15,NHT!B:F,5,FALSE) -> 58.333333
... A18: Kevin Lankinen | B18: VAN | C18: G | D18: G | E18: 7300 | F18: 11.207059 | G18: 3.3621178 | H18: 32.414119 | I18: 9.15 | J18: 2.0570593 | K18: 1.5352136 | P18: 2026-01-23 | Q18: 20260123_190750 | R18: =IFERROR(VLOOKUP($A18,Actual!$A:$D,4,FALSE),IFERROR(VLOOKUP($A18,FC!$A:$AC,29,FALSE), "Not Found")) -> -4.2 | S18: =IFERROR(VLOOKUP($A18,Actual!$A:$D,3,FALSE),"0") -> 0.0628 | T18: =VLOOKUP(A18,NHT!B:F,5,FALSE) -> 56.266667
A19: Vladislav Gavrikov | B19: NYR | C19: D | D19: D | E19: 4000 | F19: 9.0285801 | G19: 3.611432 | H19: 27.57145 | I19: 7.19 | J19: 1.8385801 | K19: 2.257145 | L19: 0.15686275 | M19: 0.17647059 | N19: 1.4705882 | O19: 0.039215686 | P19: 2026-01-23 | Q19: 20260123_190750 | R19: =IFERROR(VLOOKUP($A19,Actual!$A:$D,4,FALSE),IFERROR(VLOOKUP($A19,FC!$A:$AC,29,FALSE), "Not Found")) -> 4.5 | S19: =IFERROR(VLOOKUP($A19,Actual!$A:$D,3,FALSE),"0") -> 0.0917 | T19: =VLOOKUP(A19,NHT!B:F,5,FALSE) -> 28.033333
A20: Brandon Montour | B20: SEA | C20: D | D20: D | E20: 5400 | F20: 13.631743 | G20: 5.4526972 | H20: 39.079357 | I20: 10.08 | J20: 3.5517429 | K20: 2.5243968 | L20: 0.19354839 | M20: 0.41935484 | N20: 2.6129032 | O20: 0.19354839 | P20: 2026-01-23 | Q20: 20260123_190750 | R20: =IFERROR(VLOOKUP($A20,Actual!$A:$D,4,FALSE),IFERROR(VLOOKUP($A20,FC!$A:$AC,29,FALSE), "Not Found")) -> 5.6 | S20: =IFERROR(VLOOKUP($A20,Actual!$A:$D,3,FALSE),"0") -> 0.0555 | T20: =VLOOKUP(A20,NHT!B:F,5,FALSE) -> 27.9
A21: Filip Hronek | B21: VAN | C21: D | D21: D | E21: 3600 | F21: 9.7507779 | G21: 3.9003112 | H21: 29.376945 | I21: 7.54 | J21: 2.2107779 | K21: 2.7085494 | L21: 0.08 | M21: 0.5 | N21: 1.38 | O21: 0.18 | P21: 2026-01-23 | Q21: 20260123_190750 | R21: =IFERROR(VLOOKUP($A21,Actual!$A:$D,4,FALSE),IFERROR(VLOOKUP($A21,FC!$A:$AC,29,FALSE), "Not Found")) -> 4.1 | S21: =IFERROR(VLOOKUP($A21,Actual!$A:$D,3,FALSE),"0") -> 0.039 | T21: =VLOOKUP(A21,NHT!B:F,5,FALSE) -> 27.45
A22: Miro Heiskanen | B22: DAL | C22: D | D22: D | E22: 6400 | F22: 12.687271 | G22: 5.0749084 | H22: 36.718177 | I22: 11.16 | J22: 1.527271 | K22: 1.9823861 | L22: 0.14285714 | M22: 0.65306122 | N22: 2 | O22: 0.30612245 | P22: 2026-01-23 | Q22: 20260123_190750 | R22: =IFERROR(VLOOKUP($A22,Actual!$A:$D,4,FALSE),IFERROR(VLOOKUP($A22,FC!$A:$AC,29,FALSE), "Not Found")) -> 9.3 | S22: =IFERROR(VLOOKUP($A22,Actual!$A:$D,3,FALSE),"0") -> 0.0308 | T22: =VLOOKUP(A22,NHT!B:F,5,FALSE) -> 27
A23: Darren Raddysh | B23: TBL | C23: D | D23: D | E23: 6700 | F23: 16.470198 | G23: 6.5880791 | H23: 46.175495 | I23: 12.05 | J23: 4.4201978 | K23: 2.4582385 | L23: 0.28571429 | M23: 0.71428571 | N23: 2.4047619 | O23: 0.35714286 | P23: 2026-01-23 | Q23: 20260123_190750 | R23: =IFERROR(VLOOKUP($A23,Actual!$A:$D,4,FALSE),IFERROR(VLOOKUP($A23,FC!$A:$AC,29,FALSE), "Not Found")) -> 11.8 | S23: =IFERROR(VLOOKUP($A23,Actual!$A:$D,3,FALSE),"0") -> 0.0858 | T23: =VLOOKUP(A23,NHT!B:F,5,FALSE) -> 26.85
A24: Cale Makar | B24: COL | C24: D | D24: D | E24: 8200 | F24: 18.973209 | G24: 7.5892836 | H24: 52.433023 | I24: 14.18 | J24: 4.7932091 | K24: 2.313806 | L24: 0.29166667 | M24: 0.83333333 | N24: 2.7083333 | O24: 0.39583333 | P24: 2026-01-23 | Q24: 20260123_190750 | R24: =IFERROR(VLOOKUP($A24,Actual!$A:$D,4,FALSE),IFERROR(VLOOKUP($A24,FC!$A:$AC,29,FALSE), "Not Found")) -> 12.8 | S24: =IFERROR(VLOOKUP($A24,Actual!$A:$D,3,FALSE),"0") -> 0.1119 | T24: =VLOOKUP(A24,NHT!B:F,5,FALSE) -> 26.35
A25: Nathan MacKinnon | B25: COL | C25: C | D25: C | E25: 10200 | F25: 29.00469 | G25: 11.601876 | H25: 77.511726 | I25: 21.83 | J25: 7.1746904 | K25: 2.8435971 | L25: 0.79166667 | M25: 0.97916667 | N25: 4.6875 | O25: 0.45833333 | P25: 2026-01-23 | Q25: 20260123_190750 | R25: =IFERROR(VLOOKUP($A25,Actual!$A:$D,4,FALSE),IFERROR(VLOOKUP($A25,FC!$A:$AC,29,FALSE), "Not Found")) -> 11.5 | S25: =IFERROR(VLOOKUP($A25,Actual!$A:$D,3,FALSE),"0") -> 0.2846 | T25: =VLOOKUP(A25,NHT!B:F,5,FALSE) -> 26.25
A26: Thomas Harley | B26: DAL | C26: D | D26: D | E26: 4900 | F26: 9.0969333 | G26: 3.6387733 | H26: 27.742333 | I26: 9.34 | J26: -0.24306668 | K26: 1.856517 | L26: 0.051282051 | M26: 0.41025641 | N26: 1.5641026 | O26: 0.1025641 | P26: 2026-01-23 | Q26: 20260123_190750 | R26: =IFERROR(VLOOKUP($A26,Actual!$A:$D,4,FALSE),IFERROR(VLOOKUP($A26,FC!$A:$AC,29,FALSE), "Not Found")) -> 2.6 | S26: =IFERROR(VLOOKUP($A26,Actual!$A:$D,3,FALSE),"0") -> 0.0322 | T26: =VLOOKUP(A26,NHT!B:F,5,FALSE) -> 26.033333
A27: Kevin Bahl | B27: CGY | C27: D | D27: D | E27: 2700 | F27: 6.688025 | G27: 2.67521 | H27: 21.720063 | I27: 5.18 | J27: 1.508025 | K27: 2.4770463 | L27: 0.06122449 | M27: 0.18367347 | N27: 0.83673469 | O27: 0 | P27: 2026-01-23 | Q27: 20260123_190750 | R27: =IFERROR(VLOOKUP($A27,Actual!$A:$D,4,FALSE),IFERROR(VLOOKUP($A27,FC!$A:$AC,29,FALSE), "Not Found")) -> 3 | S27: =IFERROR(VLOOKUP($A27,Actual!$A:$D,3,FALSE),"0") -> 0.0168 | T27: =VLOOKUP(A27,NHT!B:F,5,FALSE) -> 25.766667
A28: Martin Necas | B28: COL | C28: C | D28: RW | E28: 7100 | F28: 17.378365 | G28: 6.9513458 | H28: 48.445911 | I28: 12.49 | J28: 4.8883645 | K28: 2.447657 | L28: 0.45833333 | M28: 0.79166667 | N28: 2.2916667 | O28: 0.22916667 | P28: 2026-01-23 | Q28: 20260123_190750 | R28: =IFERROR(VLOOKUP($A28,Actual!$A:$D,4,FALSE),IFERROR(VLOOKUP($A28,FC!$A:$AC,29,FALSE), "Not Found")) -> 26.5 | S28: =IFERROR(VLOOKUP($A28,Actual!$A:$D,3,FALSE),"0") -> 0.1508 | T28: =VLOOKUP(A28,NHT!B:F,5,FALSE) -> 25.266667
A29: J.J. Moser | B29: TBL | C29: D | D29: D | E29: 3100 | F29: 8.7919822 | G29: 3.5167929 | H29: 26.979956 | I29: 6.32 | J29: 2.4719822 | K29: 2.8361233 | L29: 0.10869565 | M29: 0.23913043 | N29: 1.3913043 | O29: 0 | P29: 2026-01-23 | Q29: 20260123_190750 | R29: =IFERROR(VLOOKUP($A29,Actual!$A:$D,4,FALSE),IFERROR(VLOOKUP($A29,FC!$A:$AC,29,FALSE), "Not Found")) -> 5.6 | S29: =IFERROR(VLOOKUP($A29,Actual!$A:$D,3,FALSE),"0") -> 0.0205 | T29: =VLOOKUP(A29,NHT!B:F,5,FALSE) -> 24.85
A30: Macklin Celebrini | B30: SJS | C30: C | D30: C | E30: 9000 | F30: 21.353396 | G30: 8.5413583 | H30: 58.38349 | I30: 16.92 | J30: 4.4333958 | K30: 2.3725995 | L30: 0.48979592 | M30: 0.97959184 | N30: 3.4489796 | O30: 0.42857143 | P30: 2026-01-23 | Q30: 20260123_190750 | R30: =IFERROR(VLOOKUP($A30,Actual!$A:$D,4,FALSE),IFERROR(VLOOKUP($A30,FC!$A:$AC,29,FALSE), "Not Found")) -> 23 | S30: =IFERROR(VLOOKUP($A30,Actual!$A:$D,3,FALSE),"0") -> 0.2361 | T30: =VLOOKUP(A30,NHT!B:F,5,FALSE) -> 24.6
... A287: Jack Finley | B287: TBL | C287: C | D287: C | E287: 2500 | F287: 3.7639038 | G287: 1.5055615 | H287: 14.409759 | I287: 2.33 | J287: 1.4339038 | K287: 1.5055615 | L287: 0.11764706 | M287: 0.058823529 | N287: 0.58823529 | O287: 0 | P287: 2026-01-23 | Q287: 20260123_190750 | R287: =IFERROR(VLOOKUP($A287,Actual!$A:$D,4,FALSE),IFERROR(VLOOKUP($A287,FC!$A:$AC,29,FALSE), "Not Found")) -> 0 | S287: =IFERROR(VLOOKUP($A287,Actual!$A:$D,3,FALSE),"0") -> 0 | T287: =VLOOKUP(A287,NHT!B:F,5,FALSE) -> 1.0166667

Sheet NHT
B1: Player | C1: Team | D1: Position | E1: GP | F1: TOI | G1: Goals | H1: Total Assists | I1: First Assists | J1: Second Assists | K1: Total Points | L1: IPP | M1: Shots | N1: SH% | O1: ixG | P1: iCF | Q1: iFF | R1: iSCF | S1: iHDCF | T1: Rush Attempts | U1: Rebounds Created | V1: PIM | W1: Total Penalties | X1: Minor | Y1: Major | Z1: Misconduct | AA1: Penalties Drawn | AB1: Giveaways | AC1: Takeaways | AD1: Hits | AE1: Hits Taken | AF1: Shots Blocked | AG1: Faceoffs Won | AH1: Faceoffs Lost | AI1: Faceoffs %
A2: 126 | B2: Adam Gaudette | C2: S.J | D2: R | E2: 1 | F2: 12.3 | G2: 0 | H2: 0 | I2: 0 | J2: 0 | K2: 0 | L2: - | M2: 2 | N2: 0 | O2: 0.26 | P2: 2 | Q2: 2 | R2: 1 | S2: 1 | T2: 0 | U2: 0 | V2: 0 | W2: 0 | X2: 0 | Y2: 0 | Z2: 0 | AA2: 0 | AB2: 1 | AC2: 0 | AD2: 0 | AE2: 1 | AF2: 1 | AG2: 1 | AH2: 1 | AI2: 50
A3: 257 | B3: Adam Klapka | C3: CGY | D3: R | E3: 1 | F3: 9.4333333 | G3: 0 | H3: 0 | I3: 0 | J3: 0 | K3: 0 | L3: - | M3: 2 | N3: 0 | O3: 0.61 | P3: 6 | Q3: 5 | R3: 4 | S3: 3 | T3: 0 | U3: 2 | V3: 12 | W3: 2 | X3: 1 | Y3: 0 | Z3: 1 | AA3: 0 | AB3: 0 | AC3: 0 | AD3: 3 | AE3: 1 | AF3: 1 | AG3: 0 | AH3: 0 | AI3: -
A4: 42 | B4: Adam Larsson | C4: SEA | D4: D | E4: 1 | F4: 17.566667 | G4: 0 | H4: 0 | I4: 0 | J4: 0 | K4: 0 | L4: - | M4: 0 | N4: - | O4: 0.02 | P4: 3 | Q4: 2 | R4: 0 | S4: 0 | T4: 0 | U4: 0 | V4: 0 | W4: 0 | X4: 0 | Y4: 0 | Z4: 0 | AA4: 1 | AB4: 1 | AC4: 0 | AD4: 0 | AE4: 0 | AF4: 1 | AG4: 0 | AH4: 0 | AI4: -
A5: 9 | B5: Adin Hill | C5: VGK | D5: G | E5: 1 | F5: 60
A6: 5 | B6: Alex Killorn | C6: ANA | D6: L | E6: 1 | F6: 15.283333 | G6: 0 | H6: 0 | I6: 0 | J6: 0 | K6: 0 | L6: 0 | M6: 1 | N6: 0 | O6: 0.11 | P6: 2 | Q6: 2 | R6: 1 | S6: 0 | T6: 0 | U6: 1 | V6: 2 | W6: 1 | X6: 1 | Y6: 0 | Z6: 0 | AA6: 1 | AB6: 0 | AC6: 0 | AD6: 0 | AE6: 1 | AF6: 1 | AG6: 0 | AH6: 0 | AI6: -
A7: 7 | B7: Alex Nedeljkovic | C7: S.J | D7: G | E7: 1 | F7: 60
A8: 2 | B8: Alex Ovechkin | C8: WSH | D8: L | E8: 1 | F8: 17.816667 | G8: 1 | H8: 0 | I8: 0 | J8: 0 | K8: 1 | L8: 100 | M8: 6 | N8: 16.67 | O8: 0.82 | P8: 10 | Q8: 9 | R8: 5 | S8: 2 | T8: 0 | U8: 0 | V8: 0 | W8: 0 | X8: 0 | Y8: 0 | Z8: 0 | AA8: 0 | AB8: 3 | AC8: 0 | AD8: 1 | AE8: 0 | AF8: 0 | AG8: 0 | AH8: 0 | AI8: -
A9: 196 | B9: Alex Vlasic | C9: CHI | D9: D | E9: 1 | F9: 23.7 | G9: 0 | H9: 0 | I9: 0 | J9: 0 | K9: 0 | L9: - | M9: 2 | N9: 0 | O9: 0.02 | P9: 5 | Q9: 2 | R9: 1 | S9: 0 | T9: 0 | U9: 0 | V9: 0 | W9: 0 | X9: 0 | Y9: 0 | Z9: 0 | AA9: 0 | AB9: 0 | AC9: 1 | AD9: 1 | AE9: 1 | AF9: 3 | AG9: 0 | AH9: 0 | AI9: -
A10: 219 | B10: Alexander Holtz | C10: VGK | D10: R | E10: 1 | F10: 9.75 | G10: 0 | H10: 1 | I10: 0 | J10: 1 | K10: 1 | L10: 100 | M10: 1 | N10: 0 | O10: 0.07 | P10: 2 | Q10: 2 | R10: 1 | S10: 0 | T10: 0 | U10: 0 | V10: 0 | W10: 0 | X10: 0 | Y10: 0 | Z10: 0 | AA10: 0 | AB10: 1 | AC10: 0 | AD10: 2 | AE10: 1 | AF10: 0 | AG10: 0 | AH10: 0 | AI10: -
A11: 83 | B11: Alexander Wennberg | C11: S.J | D11: C | E11: 1 | F11: 24.466667 | G11: 0 | H11: 0 | I11: 0 | J11: 0 | K11: 0 | L11: 0 | M11: 0 | N11: - | O11: 0.92 | P11: 4 | Q11: 4 | R11: 4 | S11: 3 | T11: 0 | U11: 0 | V11: 0 | W11: 0 | X11: 0 | Y11: 0 | Z11: 0 | AA11: 0 | AB11: 1 | AC11: 1 | AD11: 0 | AE11: 0 | AF11: 4 | AG11: 8 | AH11: 13 | AI11: 38.1
A12: 166 | B12: Alexey Toropchenko | C12: STL | D12: R | E12: 1 | F12: 11.916667 | G12: 0 | H12: 0 | I12: 0 | J12: 0 | K12: 0 | L12: - | M12: 0 | N12: - | O12: 0 | P12: 0 | Q12: 0 | R12: 0 | S12: 0 | T12: 0 | U12: 0 | V12: 0 | W12: 0 | X12: 0 | Y12: 0 | Z12: 0 | AA12: 0 | AB12: 0 | AC12: 1 | AD12: 1 | AE12: 1 | AF12: 1 | AG12: 0 | AH12: 0 | AI12: -
A13: 217 | B13: Alexis Lafrenière | C13: NYR | D13: L | E13: 1 | F13: 14.333333 | G13: 0 | H13: 0 | I13: 0 | J13: 0 | K13: 0 | L13: - | M13: 1 | N13: 0 | O13: 0.24 | P13: 3 | Q13: 3 | R13: 2 | S13: 1 | T13: 0 | U13: 0 | V13: 0 | W13: 0 | X13: 0 | Y13: 0 | Z13: 0 | AA13: 0 | AB13: 0 | AC13: 0 | AD13: 2 | AE13: 0 | AF13: 0 | AG13: 0 | AH13: 0 | AI13: -
A14: 205 | B14: Aliaksei Protas | C14: WSH | D14: C | E14: 1 | F14: 19.2 | G14: 1 | H14: 0 | I14: 0 | J14: 0 | K14: 1 | L14: 100 | M14: 3 | N14: 33.33 | O14: 0.59 | P14: 5 | Q14: 5 | R14: 4 | S14: 2 | T14: 0 | U14: 1 | V14: 0 | W14: 0 | X14: 0 | Y14: 0 | Z14: 0 | AA14: 0 | AB14: 1 | AC14: 1 | AD14: 1 | AE14: 2 | AF14: 2 | AG14: 0 | AH14: 0 | AI14: -
A15: 74 | B15: Andre Burakovsky | C15: CHI | D15: L | E15: 1 | F15: 21.433333 | G15: 0 | H15: 0 | I15: 0 | J15: 0 | K15: 0 | L15: - | M15: 3 | N15: 0 | O15: 0.68 | P15: 5 | Q15: 5 | R15: 5 | S15: 4 | T15: 0 | U15: 0 | V15: 0 | W15: 0 | X15: 0 | Y15: 0 | Z15: 0 | AA15: 0 | AB15: 0 | AC15: 1 | AD15: 2 | AE15: 0 | AF15: 1 | AG15: 0 | AH15: 0 | AI15: -
A16: 4 | B16: Andrei Vasilevskiy | C16: T.B | D16: G | E16: 1 | F16: 65
A17: 116 | B17: Anthony Beauvillier | C17: WSH | D17: L | E17: 1 | F17: 13.8 | G17: 0 | H17: 0 | I17: 0 | J17: 0 | K17: 0 | L17: 0 | M17: 2 | N17: 0 | O17: 0.26 | P17: 5 | Q17: 5 | R17: 4 | S17: 3 | T17: 0 | U17: 0 | V17: 0 | W17: 0 | X17: 0 | Y17: 0 | Z17: 0 | AA17: 0 | AB17: 0 | AC17: 0 | AD17: 1 | AE17: 0 | AF17: 0 | AG17: 1 | AH17: 0 | AI17: 100
A18: 122 | B18: Anthony Cirelli | C18: T.B | D18: C | E18: 1 | F18: 19.35 | G18: 0 | H18: 1 | I18: 0 | J18: 1 | K18: 1 | L18: 100 | M18: 2 | N18: 0 | O18: 0.43 | P18: 3 | Q18: 3 | R18: 3 | S18: 2 | T18: 0 | U18: 1 | V18: 0 | W18: 0 | X18: 0 | Y18: 0 | Z18: 0 | AA18: 0 | AB18: 2 | AC18: 1 | AD18: 0 | AE18: 1 | AF18: 1 | AG18: 7 | AH18: 7 | AI18: 50
A19: 5 | B19: Anthony Stolarz | C19: TOR | D19: G | E19: 1 | F19: 58.333333
A20: 67 | B20: Anton Blidh | C20: NYR | D20: L | E20: 1 | F20: 6.2333333 | G20: 0 | H20: 1 | I20: 0 | J20: 1 | K20: 1 | L20: 100 | M20: 3 | N20: 0 | O20: 0.35 | P20: 4 | Q20: 4 | R20: 3 | S20: 2 | T20: 0 | U20: 2 | V20: 0 | W20: 0 | X20: 0 | Y20: 0 | Z20: 0 | AA20: 0 | AB20: 0 | AC20: 0 | AD20: 0 | AE20: 0 | AF20: 0 | AG20: 0 | AH20: 0 | AI20: -
A21: 208 | B21: Arseny Gritsyuk | C21: N.J | D21: R | E21: 1 | F21: 13.233333 | G21: 0 | H21: 1 | I21: 1 | J21: 0 | K21: 1 | L21: 33.33 | M21: 0 | N21: - | O21: 0 | P21: 2 | Q21: 0 | R21: 0 | S21: 0 | T21: 0 | U21: 0 | V21: 0 | W21: 0 | X21: 0 | Y21: 0 | Z21: 0 | AA21: 1 | AB21: 0 | AC21: 0 | AD21: 0 | AE21: 0 | AF21: 0 | AG21: 0 | AH21: 0 | AI21: -
A22: 123 | B22: Artemi Panarin | C22: NYR | D22: L | E22: 1 | F22: 21.166667 | G22: 0 | H22: 0 | I22: 0 | J22: 0 | K22: 0 | L22: - | M22: 3 | N22: 0 | O22: 0.57 | P22: 11 | Q22: 8 | R22: 4 | S22: 1 | T22: 0 | U22: 0 | V22: 0 | W22: 0 | X22: 0 | Y22: 0 | Z22: 0 | AA22: 1 | AB22: 0 | AC22: 0 | AD22: 1 | AE22: 0 | AF22: 0 | AG22: 0 | AH22: 0 | AI22: -
A23: 77 | B23: Artturi Lehkonen | C23: COL | D23: L | E23: 1 | F23: 15.283333 | G23: 0 | H23: 0 | I23: 0 | J23: 0 | K23: 0 | L23: - | M23: 0 | N23: - | O23: 0.09 | P23: 3 | Q23: 1 | R23: 1 | S23: 1 | T23: 0 | U23: 0 | V23: 2 | W23: 1 | X23: 1 | Y23: 0 | Z23: 0 | AA23: 0 | AB23: 2 | AC23: 0 | AD23: 1 | AE23: 2 | AF23: 0 | AG23: 1 | AH23: 0 | AI23: 100
A24: 279 | B24: Artyom Levshunov | C24: CHI | D24: D | E24: 1 | F24: 21.983333 | G24: 0 | H24: 0 | I24: 0 | J24: 0 | K24: 0 | L24: - | M24: 0 | N24: - | O24: 0.02 | P24: 4 | Q24: 2 | R24: 1 | S24: 0 | T24: 0 | U24: 0 | V24: 2 | W24: 1 | X24: 1 | Y24: 0 | Z24: 0 | AA24: 0 | AB24: 4 | AC24: 0 | AD24: 2 | AE24: 1 | AF24: 0 | AG24: 0 | AH24: 0 | AI24: -
A25: 16 | B25: Arvid Soderblom | C25: CHI | D25: G | E25: 1 | F25: 65
A26: 132 | B26: Auston Matthews | C26: TOR | D26: C | E26: 1 | F26: 23.5 | G26: 0 | H26: 0 | I26: 0 | J26: 0 | K26: 0 | L26: 0 | M26: 3 | N26: 0 | O26: 0.35 | P26: 9 | Q26: 6 | R26: 4 | S26: 2 | T26: 0 | U26: 1 | V26: 0 | W26: 0 | X26: 0 | Y26: 0 | Z26: 0 | AA26: 0 | AB26: 0 | AC26: 0 | AD26: 2 | AE26: 2 | AF26: 0 | AG26: 9 | AH26: 5 | AI26: 64.29
A27: 50 | B27: Barclay Goodrow | C27: S.J | D27: C | E27: 1 | F27: 7.5166667 | G27: 0 | H27: 0 | I27: 0 | J27: 0 | K27: 0 | L27: - | M27: 0 | N27: - | O27: 0 | P27: 0 | Q27: 0 | R27: 0 | S27: 0 | T27: 0 | U27: 0 | V27: 0 | W27: 0 | X27: 0 | Y27: 0 | Z27: 0 | AA27: 0 | AB27: 0 | AC27: 0 | AD27: 0 | AE27: 0 | AF27: 2 | AG27: 0 | AH27: 0 | AI27: -
A28: 278 | B28: Beckett Sennecke | C28: ANA | D28: R | E28: 1 | F28: 13.9 | G28: 0 | H28: 0 | I28: 0 | J28: 0 | K28: 0 | L28: 0 | M28: 1 | N28: 0 | O28: 0.22 | P28: 2 | Q28: 2 | R28: 2 | S28: 2 | T28: 0 | U28: 0 | V28: 0 | W28: 0 | X28: 0 | Y28: 0 | Z28: 0 | AA28: 0 | AB28: 0 | AC28: 0 | AD28: 1 | AE28: 2 | AF28: 0 | AG28: 0 | AH28: 0 | AI28: -
A29: 66 | B29: Ben Hutton | C29: VGK | D29: D | E29: 1 | F29: 14.45 | G29: 0 | H29: 0 | I29: 0 | J29: 0 | K29: 0 | L29: 0 | M29: 0 | N29: - | O29: 0 | P29: 1 | Q29: 0 | R29: 0 | S29: 0 | T29: 0 | U29: 0 | V29: 0 | W29: 0 | X29: 0 | Y29: 0 | Z29: 0 | AA29: 0 | AB29: 2 | AC29: 1 | AD29: 0 | AE29: 1 | AF29: 0 | AG29: 0 | AH29: 0 | AI29: -
A30: 281 | B30: Berkly Catton | C30: SEA | D30: C | E30: 1 | F30: 13.616667 | G30: 0 | H30: 0 | I30: 0 | J30: 0 | K30: 0 | L30: - | M30: 1 | N30: 0 | O30: 0.13 | P30: 3 | Q30: 3 | R30: 2 | S30: 0 | T30: 0 | U30: 0 | V30: 0 | W30: 0 | X30: 0 | Y30: 0 | Z30: 0 | AA30: 1 | AB30: 1 | AC30: 0 | AD30: 0 | AE30: 2 | AF30: 0 | AG30: 0 | AH30: 0 | AI30: -
A31: 192 | B31: Bobby Brink | C31: PHI | D31: R | E31: 1 | F31: 13.216667 | G31: 1 | H31: 0 | I31: 0 | J31: 0 | K31: 1 | L31: 100 | M31: 2 | N31: 50 | O31: 0.25 | P31: 3 | Q31: 2 | R31: 2 | S31: 2 | T31: 0 | U31: 0 | V31: 0 | W31: 0 | X31: 0 | Y31: 0 | Z31: 0 | AA31: 0 | AB31: 1 | AC31: 0 | AD31: 0 | AE31: 0 | AF31: 0 | AG31: 0 | AH31: 0 | AI31: -
A32: 230 | B32: Bobby McMann | C32: TOR | D32: C | E32: 1 | F32: 17.316667 | G32: 1 | H32: 0 | I32: 0 | J32: 0 | K32: 1 | L32: 100 | M32: 4 | N32: 25 | O32: 0.36 | P32: 8 | Q32: 7 | R32: 5 | S32: 2 | T32: 0 | U32: 0 | V32: 0 | W32: 0 | X32: 0 | Y32: 0 | Z32: 0 | AA32: 0 | AB32: 0 | AC32: 0 | AD32: 0 | AE32: 0 | AF32: 0 | AG32: 0 | AH32: 0 | AI32: -
A33: 212 | B33: Braden Schneider | C33: NYR | D33: D | E33: 1 | F33: 22.766667 | G33: 0 | H33: 0 | I33: 0 | J33: 0 | K33: 0 | L33: - | M33: 0 | N33: - | O33: 0 | P33: 0 | Q33: 0 | R33: 0 | S33: 0 | T33: 0 | U33: 0 | V33: 0 | W33: 0 | X33: 0 | Y33: 0 | Z33: 0 | AA33: 0 | AB33: 3 | AC33: 0 | AD33: 0 | AE33: 1 | AF33: 2 | AG33: 0 | AH33: 0 | AI33: -
A34: 262 | B34: Braeden Bowman | C34: VGK | D34: R | E34: 1 | F34: 10.3 | G34: 1 | H34: 0 | I34: 0 | J34: 0 | K34: 1 | L34: 100 | M34: 2 | N34: 50 | O34: 0.11 | P34: 4 | Q34: 2 | R34: 3 | S34: 1 | T34: 0 | U34: 0 | V34: 0 | W34: 0 | X34: 0 | Y34: 0 | Z34: 0 | AA34: 0 | AB34: 0 | AC34: 1 | AD34: 0 | AE34: 1 | AF34: 0 | AG34: 0 | AH34: 0 | AI34: -
A35: 111 | B35: Brandon Carlo | C35: TOR | D35: D | E35: 1 | F35: 15.85 | G35: 0 | H35: 0 | I35: 0 | J35: 0 | K35: 0 | L35: 0 | M35: 0 | N35: - | O35: 0 | P35: 1 | Q35: 0 | R35: 1 | S35: 0 | T35: 0 | U35: 0 | V35: 0 | W35: 0 | X35: 0 | Y35: 0 | Z35: 0 | AA35: 0 | AB35: 0 | AC35: 0 | AD35: 2 | AE35: 2 | AF35: 0 | AG35: 0 | AH35: 0 | AI35: -
A36: 143 | B36: Brandon Duhaime | C36: WSH | D36: R | E36: 1 | F36: 9.2333333 | G36: 0 | H36: 0 | I36: 0 | J36: 0 | K36: 0 | L36: 0 | M36: 0 | N36: - | O36: 0 | P36: 0 | Q36: 0 | R36: 0 | S36: 0 | T36: 0 | U36: 0 | V36: 0 | W36: 0 | X36: 0 | Y36: 0 | Z36: 0 | AA36: 0 | AB36: 0 | AC36: 0 | AD36: 2 | AE36: 1 | AF36: 2 | AG36: 0 | AH36: 1 | AI36: 0
A37: 144 | B37: Brandon Hagel | C37: T.B | D37: L | E37: 1 | F37: 23.75 | G37: 0 | H37: 1 | I37: 1 | J37: 0 | K37: 1 | L37: 100 | M37: 2 | N37: 0 | O37: 0.45 | P37: 5 | Q37: 5 | R37: 4 | S37: 3 | T37: 0 | U37: 0 | V37: 0 | W37: 0 | X37: 0 | Y37: 0 | Z37: 0 | AA37: 0 | AB37: 0 | AC37: 1 | AD37: 1 | AE37: 1 | AF37: 0 | AG37: 0 | AH37: 0 | AI37: -
A38: 94 | B38: Brandon Montour | C38: SEA | D38: D | E38: 1 | F38: 27.9 | G38: 0 | H38: 0 | I38: 0 | J38: 0 | K38: 0 | L38: - | M38: 2 | N38: 0 | O38: 0.03 | P38: 3 | Q38: 2 | R38: 0 | S38: 0 | T38: 0 | U38: 1 | V38: 2 | W38: 1 | X38: 1 | Y38: 0 | Z38: 0 | AA38: 0 | AB38: 2 | AC38: 0 | AD38: 0 | AE38: 2 | AF38: 2 | AG38: 0 | AH38: 0 | AI38: -
A39: 186 | B39: Brayden Pachal | C39: CGY | D39: D | E39: 1 | F39: 11.7 | G39: 0 | H39: 0 | I39: 0 | J39: 0 | K39: 0 | L39: - | M39: 0 | N39: - | O39: 0 | P39: 4 | Q39: 0 | R39: 1 | S39: 0 | T39: 0 | U39: 0 | V39: 0 | W39: 0 | X39: 0 | Y39: 0 | Z39: 0 | AA39: 0 | AB39: 1 | AC39: 0 | AD39: 3 | AE39: 1 | AF39: 0 | AG39: 0 | AH39: 0 | AI39: -
A40: 15 | B40: Brayden Schenn | C40: STL | D40: C | E40: 1 | F40: 16.383333 | G40: 0 | H40: 0 | I40: 0 | J40: 0 | K40: 0 | L40: - | M40: 3 | N40: 0 | O40: 0.56 | P40: 4 | Q40: 3 | R40: 3 | S40: 3 | T40: 0 | U40: 0 | V40: 0 | W40: 0 | X40: 0 | Y40: 0 | Z40: 0 | AA40: 0 | AB40: 0 | AC40: 1 | AD40: 0 | AE40: 0 | AF40: 1 | AG40: 9 | AH40: 7 | AI40: 56.25
A41: 22 | B41: Brenden Dillon | C41: N.J | D41: D | E41: 1 | F41: 20.383333 | G41: 0 | H41: 0 | I41: 0 | J41: 0 | K41: 0 | L41: - | M41: 0 | N41: - | O41: 0 | P41: 0 | Q41: 0 | R41: 0 | S41: 0 | T41: 0 | U41: 0 | V41: 0 | W41: 0 | X41: 0 | Y41: 0 | Z41: 0 | AA41: 0 | AB41: 0 | AC41: 0 | AD41: 2 | AE41: 1 | AF41: 2 | AG41: 0 | AH41: 0 | AI41: -
A42: 239 | B42: Brennan Othmann | C42: NYR | D42: L | E42: 1 | F42: 9.0166667 | G42: 0 | H42: 0 | I42: 0 | J42: 0 | K42: 0 | L42: - | M42: 2 | N42: 0 | O42: 0.14 | P42: 2 | Q42: 2 | R42: 2 | S42: 1 | T42: 0 | U42: 0 | V42: 0 | W42: 0 | X42: 0 | Y42: 0 | Z42: 0 | AA42: 0 | AB42: 0 | AC42: 1 | AD42: 2 | AE42: 0 | AF42: 0 | AG42: 0 | AH42: 0 | AI42: -
A43: 1 | B43: Brent Burns | C43: COL | D43: D | E43: 1 | F43: 17.9 | G43: 0 | H43: 0 | I43: 0 | J43: 0 | K43: 0 | L43: - | M43: 1 | N43: 0 | O43: 0.07 | P43: 4 | Q43: 3 | R43: 0 | S43: 0 | T43: 0 | U43: 0 | V43: 0 | W43: 0 | X43: 0 | Y43: 0 | Z43: 0 | AA43: 0 | AB43: 1 | AC43: 0 | AD43: 0 | AE43: 1 | AF43: 0 | AG43: 0 | AH43: 0 | AI43: -
A44: 79 | B44: Brett Pesce | C44: N.J | D44: D | E44: 1 | F44: 23.933333 | G44: 0 | H44: 0 | I44: 0 | J44: 0 | K44: 0 | L44: 0 | M44: 0 | N44: - | O44: 0.01 | P44: 2 | Q44: 1 | R44: 0 | S44: 0 | T44: 0 | U44: 0 | V44: 0 | W44: 0 | X44: 0 | Y44: 0 | Z44: 0 | AA44: 0 | AB44: 1 | AC44: 0 | AD44: 0 | AE44: 3 | AF44: 1 | AG44: 0 | AH44: 0 | AI44: -
A45: 112 | B45: Brock Boeser | C45: VAN | D45: R | E45: 1 | F45: 20.433333 | G45: 1 | H45: 0 | I45: 0 | J45: 0 | K45: 1 | L45: 100 | M45: 2 | N45: 50 | O45: 0.34 | P45: 6 | Q45: 4 | R45: 2 | S45: 1 | T45: 0 | U45: 0 | V45: 0 | W45: 0 | X45: 0 | Y45: 0 | Z45: 0 | AA45: 0 | AB45: 1 | AC45: 0 | AD45: 0 | AE45: 0 | AF45: 0 | AG45: 0 | AH45: 1 | AI45: 0
A46: 27 | B46: Brock Nelson | C46: COL | D46: C | E46: 1 | F46: 22.633333 | G46: 0 | H46: 0 | I46: 0 | J46: 0 | K46: 0 | L46: 0 | M46: 1 | N46: 0 | O46: 0.2 | P46: 4 | Q46: 2 | R46: 3 | S46: 0 | T46: 0 | U46: 1 | V46: 0 | W46: 0 | X46: 0 | Y46: 0 | Z46: 0 | AA46: 0 | AB46: 0 | AC46: 0 | AD46: 0 | AE46: 0 | AF46: 2 | AG46: 9 | AH46: 9 | AI46: 50
A47: 161 | B47: Cale Makar | C47: COL | D47: D | E47: 1 | F47: 26.35 | G47: 1 | H47: 0 | I47: 0 | J47: 0 | K47: 1 | L47: 50 | M47: 2 | N47: 50 | O47: 0.25 | P47: 11 | Q47: 6 | R47: 5 | S47: 1 | T47: 0 | U47: 0 | V47: 0 | W47: 0 | X47: 0 | Y47: 0 | Z47: 0 | AA47: 0 | AB47: 0 | AC47: 0 | AD47: 0 | AE47: 1 | AF47: 1 | AG47: 0 | AH47: 0 | AI47: -
A48: 24 | B48: Calle Jarnkrok | C48: TOR | D48: C | E48: 1 | F48: 8.7 | G48: 0 | H48: 0 | I48: 0 | J48: 0 | K48: 0 | L48: - | M48: 1 | N48: 0 | O48: 0.02 | P48: 1 | Q48: 1 | R48: 0 | S48: 0 | T48: 0 | U48: 0 | V48: 0 | W48: 0 | X48: 0 | Y48: 0 | Z48: 0 | AA48: 0 | AB48: 0 | AC48: 0 | AD48: 0 | AE48: 0 | AF48: 0 | AG48: 0 | AH48: 0 | AI48: -
A49: 29 | B49: Cam Fowler | C49: STL | D49: D | E49: 1 | F49: 19.533333 | G49: 0 | H49: 1 | I49: 0 | J49: 1 | K49: 1 | L49: 100 | M49: 0 | N49: - | O49: 0.03 | P49: 3 | Q49: 2 | R49: 0 | S49: 0 | T49: 0 | U49: 0 | V49: 0 | W49: 0 | X49: 0 | Y49: 0 | Z49: 0 | AA49: 1 | AB49: 0 | AC49: 0 | AD49: 0 | AE49: 1 | AF49: 1 | AG49: 0 | AH49: 0 | AI49: -
A50: 191 | B50: Cam York | C50: PHI | D50: D | E50: 1 | F50: 21.55 | G50: 0 | H50: 1 | I50: 0 | J50: 1 | K50: 1 | L50: 33.33 | M50: 1 | N50: 0 | O50: 0.04 | P50: 3 | Q50: 1 | R50: 1 | S50: 0 | T50: 0 | U50: 0 | V50: 0 | W50: 0 | X50: 0 | Y50: 0 | Z50: 0 | AA50: 0 | AB50: 0 | AC50: 0 | AD50: 1 | AE50: 2 | AF50: 2 | AG50: 0 | AH50: 0 | AI50: -
A51: 134 | B51: Carl Grundstrom | C51: PHI | D51: R | E51: 1 | F51: 11.5 | G51: 0 | H51: 0 | I51: 0 | J51: 0 | K51: 0 | L51: - | M51: 0 | N51: - | O51: 0 | P51: 0 | Q51: 0 | R51: 0 | S51: 0 | T51: 0 | U51: 0 | V51: 0 | W51: 0 | X51: 0 | Y51: 0 | Z51: 0 | AA51: 0 | AB51: 0 | AC51: 0 | AD51: 3 | AE51: 3 | AF51: 0 | AG51: 0 | AH51: 0 | AI51: -
A52: 69 | B52: Carson Soucy | C52: NYR | D52: D | E52: 1 | F52: 12.833333 | G52: 0 | H52: 0 | I52: 0 | J52: 0 | K52: 0 | L52: 0 | M52: 0 | N52: - | O52: 0 | P52: 0 | Q52: 0 | R52: 0 | S52: 0 | T52: 0 | U52: 0 | V52: 2 | W52: 1 | X52: 1 | Y52: 0 | Z52: 0 | AA52: 0 | AB52: 2 | AC52: 0 | AD52: 1 | AE52: 0 | AF52: 0 | AG52: 0 | AH52: 0 | AI52: -
A53: 62 | B53: Chandler Stephenson | C53: SEA | D53: C | E53: 1 | F53: 15.9 | G53: 0 | H53: 0 | I53: 0 | J53: 0 | K53: 0 | L53: - | M53: 0 | N53: - | O53: 0 | P53: 0 | Q53: 0 | R53: 0 | S53: 0 | T53: 0 | U53: 0 | V53: 0 | W53: 0 | X53: 0 | Y53: 0 | Z53: 0 | AA53: 0 | AB53: 1 | AC53: 0 | AD53: 0 | AE53: 1 | AF53: 1 | AG53: 10 | AH53: 7 | AI53: 58.82
A54: 167 | B54: Charle-Edouard D'Astous | C54: T.B | D54: D | E54: 1 | F54: 20.85 | G54: 0 | H54: 0 | I54: 0 | J54: 0 | K54: 0 | L54: 0 | M54: 0 | N54: - | O54: 0.05 | P54: 3 | Q54: 2 | R54: 0 | S54: 0 | T54: 0 | U54: 0 | V54: 0 | W54: 0 | X54: 0 | Y54: 0 | Z54: 0 | AA54: 0 | AB54: 2 | AC54: 0 | AD54: 4 | AE54: 0 | AF54: 1 | AG54: 0 | AH54: 0 | AI54: -
A55: 18 | B55: Chris Kreider | C55: ANA | D55: L | E55: 1 | F55: 16.8 | G55: 1 | H55: 0 | I55: 0 | J55: 0 | K55: 1 | L55: 50 | M55: 1 | N55: 100 | O55: 0.49 | P55: 4 | Q55: 2 | R55: 4 | S55: 2 | T55: 0 | U55: 0 | V55: 0 | W55: 0 | X55: 0 | Y55: 0 | Z55: 0 | AA55: 0 | AB55: 0 | AC55: 0 | AD55: 0 | AE55: 1 | AF55: 0 | AG55: 0 | AH55: 1 | AI55: 0
A56: 96 | B56: Christian Dvorak | C56: PHI | D56: C | E56: 1 | F56: 20.8 | G56: 0 | H56: 0 | I56: 0 | J56: 0 | K56: 0 | L56: - | M56: 3 | N56: 0 | O56: 0.54 | P56: 5 | Q56: 4 | R56: 4 | S56: 2 | T56: 1 | U56: 0 | V56: 0 | W56: 0 | X56: 0 | Y56: 0 | Z56: 0 | AA56: 0 | AB56: 6 | AC56: 0 | AD56: 0 | AE56: 0 | AF56: 1 | AG56: 7 | AH56: 8 | AI56: 46.67
A57: 149 | B57: Cody Glass | C57: N.J | D57: C | E57: 1 | F57: 12.466667 | G57: 2 | H57: 1 | I57: 0 | J57: 1 | K57: 3 | L57: 100 | M57: 4 | N57: 50 | O57: 0.38 | P57: 4 | Q57: 4 | R57: 3 | S57: 3 | T57: 0 | U57: 0 | V57: 0 | W57: 0 | X57: 0 | Y57: 0 | Z57: 0 | AA57: 0 | AB57: 0 | AC57: 0 | AD57: 0 | AE57: 0 | AF57: 2 | AG57: 4 | AH57: 7 | AI57: 36.36
A58: 35 | B58: Colin Blackwell | C58: DAL | D58: C | E58: 1 | F58: 10.633333 | G58: 0 | H58: 0 | I58: 0 | J58: 0 | K58: 0 | L58: - | M58: 0 | N58: - | O58: 0 | P58: 0 | Q58: 0 | R58: 0 | S58: 0 | T58: 0 | U58: 0 | V58: 0 | W58: 0 | X58: 0 | Y58: 0 | Z58: 0 | AA58: 0 | AB58: 0 | AC58: 1 | AD58: 1 | AE58: 1 | AF58: 0 | AG58: 4 | AH58: 2 | AI58: 66.67
A59: 286 | B59: Collin Graf | C59: S.J | D59: R | E59: 1 | F59: 19.216667 | G59: 0 | H59: 2 | I59: 0 | J59: 2 | K59: 2 | L59: 100 | M59: 0 | N59: - | O59: 0.02 | P59: 1 | Q59: 1 | R59: 0 | S59: 0 | T59: 0 | U59: 0 | V59: 2 | W59: 1 | X59: 1 | Y59: 0 | Z59: 0 | AA59: 0 | AB59: 2 | AC59: 1 | AD59: 2 | AE59: 0 | AF59: 0 | AG59: 0 | AH59: 0 | AI59: -
A60: 60 | B60: Colton Parayko | C60: STL | D60: D | E60: 1 | F60: 21.883333 | G60: 0 | H60: 0 | I60: 0 | J60: 0 | K60: 0 | L60: - | M60: 1 | N60: 0 | O60: 0.07 | P60: 5 | Q60: 3 | R60: 0 | S60: 0 | T60: 0 | U60: 0 | V60: 0 | W60: 0 | X60: 0 | Y60: 0 | Z60: 0 | AA60: 0 | AB60: 3 | AC60: 1 | AD60: 2 | AE60: 2 | AF60: 3 | AG60: 0 | AH60: 0 | AI60: -
A61: 264 | B61: Connor Bedard | C61: CHI | D61: C | E61: 1 | F61: 21.6 | G61: 0 | H61: 0 | I61: 0 | J61: 0 | K61: 0 | L61: - | M61: 0 | N61: - | O61: 0 | P61: 1 | Q61: 0 | R61: 0 | S61: 0 | T61: 0 | U61: 0 | V61: 0 | W61: 0 | X61: 0 | Y61: 0 | Z61: 0 | AA61: 0 | AB61: 4 | AC61: 0 | AD61: 1 | AE61: 0 | AF61: 1 | AG61: 0 | AH61: 0 | AI61: -
A62: 65 | B62: Connor Brown | C62: N.J | D62: R | E62: 1 | F62: 18.616667 | G62: 1 | H62: 0 | I62: 0 | J62: 0 | K62: 1 | L62: 50 | M62: 1 | N62: 100 | O62: 0.33 | P62: 4 | Q62: 3 | R62: 2 | S62: 1 | T62: 0 | U62: 0 | V62: 0 | W62: 0 | X62: 0 | Y62: 0 | Z62: 0 | AA62: 0 | AB62: 1 | AC62: 0 | AD62: 0 | AE62: 1 | AF62: 1 | AG62: 0 | AH62: 1 | AI62: 0
A63: 197 | B63: Connor McMichael | C63: WSH | D63: C | E63: 1 | F63: 12.5 | G63: 0 | H63: 0 | I63: 0 | J63: 0 | K63: 0 | L63: - | M63: 1 | N63: 0 | O63: 0.18 | P63: 1 | Q63: 1 | R63: 1 | S63: 1 | T63: 0 | U63: 0 | V63: 0 | W63: 0 | X63: 0 | Y63: 0 | Z63: 0 | AA63: 0 | AB63: 2 | AC63: 0 | AD63: 0 | AE63: 1 | AF63: 0 | AG63: 0 | AH63: 0 | AI63: -
A64: 49 | B64: Connor Murphy | C64: CHI | D64: D | E64: 1 | F64: 17.566667 | G64: 0 | H64: 0 | I64: 0 | J64: 0 | K64: 0 | L64: - | M64: 0 | N64: - | O64: 0.03 | P64: 1 | Q64: 1 | R64: 0 | S64: 0 | T64: 0 | U64: 0 | V64: 0 | W64: 0 | X64: 0 | Y64: 0 | Z64: 0 | AA64: 0 | AB64: 0 | AC64: 0 | AD64: 0 | AE64: 1 | AF64: 3 | AG64: 0 | AH64: 0 | AI64: -
A65: 213 | B65: Connor Zary | C65: CGY | D65: C | E65: 1 | F65: 14.4 | G65: 0 | H65: 1 | I65: 1 | J65: 0 | K65: 1 | L65: 100 | M65: 0 | N65: - | O65: 0.21 | P65: 2 | Q65: 1 | R65: 2 | S65: 1 | T65: 0 | U65: 0 | V65: 0 | W65: 0 | X65: 0 | Y65: 0 | Z65: 0 | AA65: 0 | AB65: 0 | AC65: 0 | AD65: 1 | AE65: 0 | AF65: 1 | AG65: 4 | AH65: 7 | AI65: 36.36
A66: 125 | B66: Conor Garland | C66: VAN | D66: R | E66: 1 | F66: 15.483333 | G66: 0 | H66: 0 | I66: 0 | J66: 0 | K66: 0 | L66: - | M66: 0 | N66: - | O66: 0.09 | P66: 3 | Q66: 1 | R66: 1 | S66: 0 | T66: 0 | U66: 0 | V66: 4 | W66: 1 | X66: 1 | Y66: 0 | Z66: 0 | AA66: 0 | AB66: 1 | AC66: 0 | AD66: 0 | AE66: 1 | AF66: 0 | AG66: 1 | AH66: 1 | AI66: 50
A67: 248 | B67: Cutter Gauthier | C67: ANA | D67: L | E67: 1 | F67: 17.216667 | G67: 1 | H67: 1 | I67: 1 | J67: 0 | K67: 2 | L67: 100 | M67: 7 | N67: 14.29 | O67: 0.23 | P67: 9 | Q67: 9 | R67: 2 | S67: 0 | T67: 0 | U67: 3 | V67: 0 | W67: 0 | X67: 0 | Y67: 0 | Z67: 0 | AA67: 0 | AB67: 1 | AC67: 0 | AD67: 2 | AE67: 0 | AF67: 0 | AG67: 2 | AH67: 1 | AI67: 66.67
A68: 267 | B68: Dalibor Dvorsky | C68: STL | D68: R | E68: 1 | F68: 13.35 | G68: 1 | H68: 0 | I68: 0 | J68: 0 | K68: 1 | L68: 100 | M68: 1 | N68: 100 | O68: 0.23 | P68: 3 | Q68: 2 | R68: 2 | S68: 1 | T68: 0 | U68: 0 | V68: 0 | W68: 0 | X68: 0 | Y68: 0 | Z68: 0 | AA68: 0 | AB68: 0 | AC68: 0 | AD68: 1 | AE68: 0 | AF68: 0 | AG68: 6 | AH68: 10 | AI68: 37.5
A69: 98 | B69: Darren Raddysh | C69: T.B | D69: D | E69: 1 | F69: 26.85 | G69: 0 | H69: 0 | I69: 0 | J69: 0 | K69: 0 | L69: - | M69: 5 | N69: 0 | O69: 0.27 | P69: 8 | Q69: 7 | R69: 3 | S69: 0 | T69: 0 | U69: 1 | V69: 2 | W69: 1 | X69: 1 | Y69: 0 | Z69: 0 | AA69: 0 | AB69: 2 | AC69: 0 | AD69: 1 | AE69: 1 | AF69: 1 | AG69: 0 | AH69: 0 | AI69: -
A70: 163 | B70: David Kampf | C70: VAN | D70: C | E70: 1 | F70: 12.533333 | G70: 0 | H70: 0 | I70: 0 | J70: 0 | K70: 0 | L70: 0 | M70: 0 | N70: - | O70: 0 | P70: 0 | Q70: 0 | R70: 0 | S70: 0 | T70: 0 | U70: 0 | V70: 0 | W70: 0 | X70: 0 | Y70: 0 | Z70: 0 | AA70: 0 | AB70: 0 | AC70: 0 | AD70: 0 | AE70: 1 | AF70: 0 | AG70: 3 | AH70: 6 | AI70: 33.33
A71: 218 | B71: Dawson Mercer | C71: N.J | D71: C | E71: 1 | F71: 19.05 | G71: 0 | H71: 0 | I71: 0 | J71: 0 | K71: 0 | L71: - | M71: 0 | N71: - | O71: 0.09 | P71: 1 | Q71: 1 | R71: 1 | S71: 1 | T71: 0 | U71: 0 | V71: 0 | W71: 0 | X71: 0 | Y71: 0 | Z71: 0 | AA71: 0 | AB71: 0 | AC71: 0 | AD71: 1 | AE71: 3 | AF71: 1 | AG71: 0 | AH71: 1 | AI71: 0
A72: 247 | B72: Declan Carlile | C72: T.B | D72: D | E72: 1 | F72: 12.35 | G72: 0 | H72: 0 | I72: 0 | J72: 0 | K72: 0 | L72: - | M72: 0 | N72: - | O72: 0 | P72: 2 | Q72: 0 | R72: 1 | S72: 0 | T72: 0 | U72: 0 | V72: 0 | W72: 0 | X72: 0 | Y72: 0 | Z72: 0 | AA72: 0 | AB72: 0 | AC72: 0 | AD72: 0 | AE72: 1 | AF72: 1 | AG72: 0 | AH72: 0 | AI72: -
A73: 263 | B73: Denver Barkey | C73: PHI | D73: C | E73: 1 | F73: 13.85 | G73: 1 | H73: 1 | I73: 1 | J73: 0 | K73: 2 | L73: 66.67 | M73: 2 | N73: 50 | O73: 0.09 | P73: 2 | Q73: 2 | R73: 1 | S73: 0 | T73: 0 | U73: 0 | V73: 2 | W73: 1 | X73: 1 | Y73: 0 | Z73: 0 | AA73: 0 | AB73: 2 | AC73: 0 | AD73: 0 | AE73: 0 | AF73: 0 | AG73: 0 | AH73: 0 | AI73: -
A74: 15 | B74: Devin Cooley | C74: CGY | D74: G | E74: 1 | F74: 58.333333
A75: 20 | B75: Dmitry Orlov | C75: S.J | D75: D | E75: 1 | F75: 20.666667 | G75: 0 | H75: 0 | I75: 0 | J75: 0 | K75: 0 | L75: 0 | M75: 1 | N75: 0 | O75: 0.06 | P75: 2 | Q75: 2 | R75: 0 | S75: 0 | T75: 0 | U75: 0 | V75: 0 | W75: 0 | X75: 0 | Y75: 0 | Z75: 0 | AA75: 0 | AB75: 0 | AC75: 1 | AD75: 2 | AE75: 1 | AF75: 0 | AG75: 0 | AH75: 0 | AI75: -
A76: 261 | B76: Dominic James | C76: T.B | D76: C | E76: 1 | F76: 12.633333 | G76: 0 | H76: 0 | I76: 0 | J76: 0 | K76: 0 | L76: - | M76: 2 | N76: 0 | O76: 0.16 | P76: 3 | Q76: 3 | R76: 2 | S76: 1 | T76: 0 | U76: 0 | V76: 0 | W76: 0 | X76: 0 | Y76: 0 | Z76: 0 | AA76: 0 | AB76: 3 | AC76: 0 | AD76: 2 | AE76: 1 | AF76: 1 | AG76: 4 | AH76: 5 | AI76: 44.44
A77: 46 | B77: Dougie Hamilton | C77: N.J | D77: D | E77: 1 | F77: 21.366667 | G77: 0 | H77: 1 | I77: 0 | J77: 1 | K77: 1 | L77: 33.33 | M77: 1 | N77: 0 | O77: 0.01 | P77: 3 | Q77: 1 | R77: 1 | S77: 0 | T77: 0 | U77: 0 | V77: 0 | W77: 0 | X77: 0 | Y77: 0 | Z77: 0 | AA77: 0 | AB77: 1 | AC77: 0 | AD77: 0 | AE77: 0 | AF77: 1 | AG77: 0 | AH77: 0 | AI77: -
A78: 195 | B78: Drew Helleson | C78: ANA | D78: D | E78: 1 | F78: 18.783333 | G78: 0 | H78: 1 | I78: 0 | J78: 1 | K78: 1 | L78: 50 | M78: 1 | N78: 0 | O78: 0.03 | P78: 5 | Q78: 3 | R78: 0 | S78: 0 | T78: 1 | U78: 0 | V78: 0 | W78: 0 | X78: 0 | Y78: 0 | Z78: 0 | AA78: 0 | AB78: 1 | AC78: 1 | AD78: 1 | AE78: 6 | AF78: 1 | AG78: 0 | AH78: 0 | AI78: -
A79: 210 | B79: Drew O'Connor | C79: VAN | D79: L | E79: 1 | F79: 18.183333 | G79: 0 | H79: 1 | I79: 1 | J79: 0 | K79: 1 | L79: 50 | M79: 2 | N79: 0 | O79: 0.45 | P79: 3 | Q79: 3 | R79: 3 | S79: 3 | T79: 0 | U79: 0 | V79: 0 | W79: 0 | X79: 0 | Y79: 0 | Z79: 0 | AA79: 1 | AB79: 0 | AC79: 1 | AD79: 0 | AE79: 0 | AF79: 0 | AG79: 0 | AH79: 0 | AI79: -
A80: 110 | B80: Dylan Strome | C80: WSH | D80: C | E80: 1 | F80: 18.116667 | G80: 0 | H80: 1 | I80: 1 | J80: 0 | K80: 1 | L80: 100 | M80: 4 | N80: 0 | O80: 0.81 | P80: 5 | Q80: 4 | R80: 3 | S80: 2 | T80: 0 | U80: 2 | V80: 0 | W80: 0 | X80: 0 | Y80: 0 | Z80: 0 | AA80: 0 | AB80: 0 | AC80: 0 | AD80: 0 | AE80: 0 | AF80: 1 | AG80: 16 | AH80: 4 | AI80: 80
A81: 266 | B81: Easton Cowan | C81: TOR | D81: R | E81: 1 | F81: 10.85 | G81: 0 | H81: 0 | I81: 0 | J81: 0 | K81: 0 | L81: - | M81: 1 | N81: 0 | O81: 0.08 | P81: 1 | Q81: 1 | R81: 1 | S81: 1 | T81: 0 | U81: 0 | V81: 0 | W81: 0 | X81: 0 | Y81: 0 | Z81: 0 | AA81: 0 | AB81: 0 | AC81: 0 | AD81: 1 | AE81: 0 | AF81: 1 | AG81: 0 | AH81: 0 | AI81: -
A82: 152 | B82: Eeli Tolvanen | C82: SEA | D82: R | E82: 1 | F82: 15.566667 | G82: 0 | H82: 0 | I82: 0 | J82: 0 | K82: 0 | L82: - | M82: 3 | N82: 0 | O82: 0.26 | P82: 5 | Q82: 5 | R82: 3 | S82: 2 | T82: 0 | U82: 0 | V82: 0 | W82: 0 | X82: 0 | Y82: 0 | Z82: 0 | AA82: 0 | AB82: 0 | AC82: 0 | AD82: 5 | AE82: 1 | AF82: 1 | AG82: 0 | AH82: 0 | AI82: -
A83: 153 | B83: Elias Pettersson | C83: VAN | D83: C | E83: 1 | F83: 14.3 | G83: 0 | H83: 1 | I83: 1 | J83: 0 | K83: 1 | L83: 100 | M83: 0 | N83: - | O83: 0.02 | P83: 1 | Q83: 1 | R83: 0 | S83: 0 | T83: 0 | U83: 0 | V83: 0 | W83: 0 | X83: 0 | Y83: 0 | Z83: 0 | AA83: 1 | AB83: 1 | AC83: 0 | AD83: 0 | AE83: 0 | AF83: 2 | AG83: 6 | AH83: 8 | AI83: 42.86
A84: 259 | B84: Elias Pettersson | C84: VAN | D84: D | E84: 1 | F84: 16.133333 | G84: 0 | H84: 0 | I84: 0 | J84: 0 | K84: 0 | L84: - | M84: 0 | N84: - | O84: 0 | P84: 1 | Q84: 0 | R84: 0 | S84: 0 | T84: 0 | U84: 0 | V84: 0 | W84: 0 | X84: 0 | Y84: 0 | Z84: 0 | AA84: 0 | AB84: 2 | AC84: 0 | AD84: 5 | AE84: 1 | AF84: 4 | AG84: 0 | AH84: 0 | AI84: -
A85: 220 | B85: Emil Andrae | C85: PHI | D85: D | E85: 1 | F85: 13.333333 | G85: 0 | H85: 1 | I85: 1 | J85: 0 | K85: 1 | L85: 100 | M85: 0 | N85: - | O85: 0 | P85: 0 | Q85: 0 | R85: 0 | S85: 0 | T85: 0 | U85: 0 | V85: 2 | W85: 1 | X85: 1 | Y85: 0 | Z85: 0 | AA85: 0 | AB85: 1 | AC85: 0 | AD85: 1 | AE85: 0 | AF85: 0 | AG85: 0 | AH85: 0 | AI85: -
A86: 105 | B86: Erik Cernak | C86: T.B | D86: D | E86: 1 | F86: 19.55 | G86: 0 | H86: 0 | I86: 0 | J86: 0 | K86: 0 | L86: 0 | M86: 1 | N86: 0 | O86: 0.08 | P86: 4 | Q86: 2 | R86: 0 | S86: 0 | T86: 0 | U86: 0 | V86: 0 | W86: 0 | X86: 0 | Y86: 0 | Z86: 0 | AA86: 0 | AB86: 2 | AC86: 0 | AD86: 4 | AE86: 0 | AF86: 0 | AG86: 0 | AH86: 0 | AI86: -
A87: 61 | B87: Esa Lindell | C87: DAL | D87: D | E87: 1 | F87: 22.266667 | G87: 0 | H87: 0 | I87: 0 | J87: 0 | K87: 0 | L87: - | M87: 2 | N87: 0 | O87: 0.15 | P87: 4 | Q87: 2 | R87: 2 | S87: 0 | T87: 0 | U87: 1 | V87: 0 | W87: 0 | X87: 0 | Y87: 0 | Z87: 0 | AA87: 0 | AB87: 0 | AC87: 1 | AD87: 0 | AE87: 2 | AF87: 5 | AG87: 0 | AH87: 0 | AI87: -
A88: 256 | B88: Ethen Frank | C88: WSH | D88: C | E88: 1 | F88: 13.833333 | G88: 0 | H88: 0 | I88: 0 | J88: 0 | K88: 0 | L88: - | M88: 0 | N88: - | O88: 0 | P88: 0 | Q88: 0 | R88: 0 | S88: 0 | T88: 0 | U88: 0 | V88: 0 | W88: 0 | X88: 0 | Y88: 0 | Z88: 0 | AA88: 0 | AB88: 1 | AC88: 0 | AD88: 0 | AE88: 2 | AF88: 2 | AG88: 0 | AH88: 1 | AI88: 0
A89: 14 | B89: Evander Kane | C89: VAN | D89: L | E89: 1 | F89: 15.55 | G89: 0 | H89: 0 | I89: 0 | J89: 0 | K89: 0 | L89: 0 | M89: 1 | N89: 0 | O89: 0.32 | P89: 2 | Q89: 2 | R89: 2 | S89: 2 | T89: 0 | U89: 1 | V89: 0 | W89: 0 | X89: 0 | Y89: 0 | Z89: 0 | AA89: 0 | AB89: 1 | AC89: 0 | AD89: 1 | AE89: 1 | AF89: 1 | AG89: 0 | AH89: 0 | AI89: -
A90: 7 | B90: Evgenii Dadonov | C90: N.J | D90: L | E90: 1 | F90: 11.533333 | G90: 0 | H90: 0 | I90: 0 | J90: 0 | K90: 0 | L90: - | M90: 0 | N90: - | O90: 0 | P90: 0 | Q90: 0 | R90: 0 | S90: 0 | T90: 0 | U90: 0 | V90: 2 | W90: 1 | X90: 1 | Y90: 0 | Z90: 0 | AA90: 0 | AB90: 1 | AC90: 0 | AD90: 0 | AE90: 0 | AF90: 1 | AG90: 0 | AH90: 0 | AI90: -
A91: 162 | B91: Filip Chytil | C91: VAN | D91: C | E91: 1 | F91: 18.483333 | G91: 0 | H91: 0 | I91: 0 | J91: 0 | K91: 0 | L91: 0 | M91: 2 | N91: 0 | O91: 0.17 | P91: 4 | Q91: 3 | R91: 2 | S91: 0 | T91: 0 | U91: 0 | V91: 0 | W91: 0 | X91: 0 | Y91: 0 | Z91: 0 | AA91: 0 | AB91: 3 | AC91: 0 | AD91: 1 | AE91: 1 | AF91: 0 | AG91: 8 | AH91: 5 | AI91: 61.54
A92: 141 | B92: Filip Hronek | C92: VAN | D92: D | E92: 1 | F92: 27.45 | G92: 0 | H92: 0 | I92: 0 | J92: 0 | K92: 0 | L92: 0 | M92: 1 | N92: 0 | O92: 0.05 | P92: 3 | Q92: 2 | R92: 0 | S92: 0 | T92: 0 | U92: 0 | V92: 0 | W92: 0 | X92: 0 | Y92: 0 | Z92: 0 | AA92: 0 | AB92: 2 | AC92: 2 | AD92: 3 | AE92: 0 | AF92: 2 | AG92: 0 | AH92: 0 | AI92: -
A93: 251 | B93: Frank Nazar | C93: CHI | D93: C | E93: 1 | F93: 20.616667 | G93: 0 | H93: 0 | I93: 0 | J93: 0 | K93: 0 | L93: - | M93: 3 | N93: 0 | O93: 0.34 | P93: 6 | Q93: 4 | R93: 4 | S93: 2 | T93: 1 | U93: 0 | V93: 0 | W93: 0 | X93: 0 | Y93: 0 | Z93: 0 | AA93: 0 | AB93: 1 | AC93: 1 | AD93: 0 | AE93: 2 | AF93: 0 | AG93: 9 | AH93: 5 | AI93: 64.29
A94: 88 | B94: Freddy Gaudreau | C94: SEA | D94: C | E94: 1 | F94: 13.416667 | G94: 0 | H94: 0 | I94: 0 | J94: 0 | K94: 0 | L94: - | M94: 1 | N94: 0 | O94: 0.02 | P94: 1 | Q94: 1 | R94: 0 | S94: 0 | T94: 1 | U94: 0 | V94: 0 | W94: 0 | X94: 0 | Y94: 0 | Z94: 0 | AA94: 0 | AB94: 0 | AC94: 0 | AD94: 0 | AE94: 1 | AF94: 0 | AG94: 2 | AH94: 3 | AI94: 40
A95: 272 | B95: Gabe Perreault | C95: NYR | D95: R | E95: 1 | F95: 13.666667 | G95: 0 | H95: 0 | I95: 0 | J95: 0 | K95: 0 | L95: - | M95: 1 | N95: 0 | O95: 0.34 | P95: 2 | Q95: 2 | R95: 2 | S95: 1 | T95: 0 | U95: 2 | V95: 2 | W95: 1 | X95: 1 | Y95: 0 | Z95: 0 | AA95: 0 | AB95: 1 | AC95: 0 | AD95: 2 | AE95: 0 | AF95: 1 | AG95: 0 | AH95: 0 | AI95: -
A96: 229 | B96: Gage Goncalves | C96: T.B | D96: C | E96: 1 | F96: 15.266667 | G96: 0 | H96: 0 | I96: 0 | J96: 0 | K96: 0 | L96: - | M96: 2 | N96: 0 | O96: 0.18 | P96: 3 | Q96: 3 | R96: 3 | S96: 0 | T96: 0 | U96: 0 | V96: 0 | W96: 0 | X96: 0 | Y96: 0 | Z96: 0 | AA96: 1 | AB96: 0 | AC96: 0 | AD96: 1 | AE96: 1 | AF96: 0 | AG96: 0 | AH96: 0 | AI96: -
A97: 87 | B97: Garnet Hathaway | C97: PHI | D97: R | E97: 1 | F97: 8.1666667 | G97: 0 | H97: 1 | I97: 0 | J97: 1 | K97: 1 | L97: 100 | M97: 0 | N97: - | O97: 0.01 | P97: 1 | Q97: 1 | R97: 0 | S97: 0 | T97: 0 | U97: 1 | V97: 0 | W97: 0 | X97: 0 | Y97: 0 | Z97: 0 | AA97: 0 | AB97: 1 | AC97: 0 | AD97: 3 | AE97: 3 | AF97: 1 | AG97: 0 | AH97: 1 | AI97: 0
A98: 265 | B98: Gavin Brindley | C98: COL | D98: C | E98: 1 | F98: 11 | G98: 0 | H98: 0 | I98: 0 | J98: 0 | K98: 0 | L98: - | M98: 3 | N98: 0 | O98: 0.37 | P98: 3 | Q98: 3 | R98: 3 | S98: 1 | T98: 0 | U98: 1 | V98: 0 | W98: 0 | X98: 0 | Y98: 0 | Z98: 0 | AA98: 0 | AB98: 1 | AC98: 0 | AD98: 0 | AE98: 3 | AF98: 1 | AG98: 0 | AH98: 0 | AI98: -
A99: 223 | B99: Hendrix Lapierre | C99: WSH | D99: C | E99: 1 | F99: 9.5333333 | G99: 1 | H99: 0 | I99: 0 | J99: 0 | K99: 1 | L99: 100 | M99: 3 | N99: 33.33 | O99: 0.35 | P99: 3 | Q99: 3 | R99: 3 | S99: 3 | T99: 0 | U99: 0 | V99: 2 | W99: 1 | X99: 1 | Y99: 0 | Z99: 0 | AA99: 0 | AB99: 1 | AC99: 0 | AD99: 0 | AE99: 1 | AF99: 0 | AG99: 2 | AH99: 4 | AI99: 33.33
A100: 228 | B100: Ian Moore | C100: ANA | D100: D | E100: 1 | F100: 14.316667 | G100: 0 | H100: 1 | I100: 1 | J100: 0 | K100: 1 | L100: 100 | M100: 1 | N100: 0 | O100: 0.06 | P100: 3 | Q100: 3 | R100: 1 | S100: 0 | T100: 1 | U100: 0 | V100: 0 | W100: 0 | X100: 0 | Y100: 0 | Z100: 0 | AA100: 0 | AB100: 0 | AC100: 1 | AD100: 0 | AE100: 0 | AF100: 1 | AG100: 0 | AH100: 0 | AI100: -
...

Sheet FC
A1: Player | B1: Inj | C1: Likes | D1: Pos | E1: Salary | F1: Team | G1: Opp | H1: Time | I1: Fav. | J1: Win % | K1: Spread | L1: Total | M1: TeamGoal | N1: OppGoal | O1: Start/Line | P1: PP Unit | Q1: avg TOI | R1: Avg | S1: STDV | T1: Ceiling | U1: FC Proj | V1: My Proj | W1: Exp. | X1: Used | Y1: Con. | Z1: Value | AA1: Own% | AB1: TOI | AC1: Score | AD1: Val
A2: Aatu Raty | C2: 0 | D2: C | E2: 2500 | F2: VAN | G2: vs NJ | H2: 21:59:59.9999999999968050 | I2: N | J2: 0.528 | K2: 89.5 | L2: 6 | M2: 2.77 | N2: 3 | Q2: 12:07:59.99999999999829150 | R2: 3.8 | S2: 5.17 | T2: 0 | U2: 0 | V2: 0 | W2: 100 | Y2: 32 | Z2: 0 | AA2: 0
A3: Adam Edstrom | C3: 0 | D3: C | E3: 2500 | F3: NYR | G3: @ SJ | H3: 21:59:59.9999999999968050 | I3: N | J3: 0.554 | K3: 80.5 | L3: 6.5 | M3: 3.25 | N3: 3.38 | Q3: 09:41:00.00000000000085425 | R3: 3.6 | S3: 3.99 | T3: 0 | U3: 0 | V3: 0 | W3: 100 | Y3: 45 | Z3: 0 | AA3: 0
A4: Adam Erne | C4: 0 | D4: W | E4: 2500 | F4: DAL | G4: vs STL | H4: 20:00:00.0000000000031950 | I4: Y | J4: 0.486 | K4: -94.5 | L4: 5.5 | M4: 3.07 | N4: 2.75 | Q4: 09:25:59.99999999999925675 | R4: 3.8 | S4: 4.24 | T4: 0 | U4: 0 | V4: 0 | W4: 100 | Y4: 44 | Z4: 0 | AA4: 0
A5: Adam Fox | C5: 0 | D5: D | E5: 6500 | F5: NYR | G5: @ SJ | H5: 21:59:59.9999999999968050 | I5: N | J5: 0.554 | K5: 80.5 | L5: 6.5 | M5: 3.25 | N5: 3.38 | Q5: 23:26:59.999999999997441975 | R5: 11 | S5: 6.33 | T5: 0 | U5: 0 | V5: 0 | W5: 100 | Y5: 71 | Z5: 0 | AA5: 0
A6: Adam Gaudette | C6: 0 | D6: W | E6: 2800 | F6: SJ | G6: vs NYR | H6: 21:59:59.9999999999968050 | I6: Y | J6: 0.446 | K6: -80.5 | L6: 6.5 | M6: 3.38 | N6: 3.25 | O6: 3 | Q6: 12:00:00.000 | R6: 6.1 | S6: 5.98 | T6: 19.78 | U6: 7.82 | V6: 7.82 | W6: 100 | Y6: 51 | Z6: 2.8 | AA6: 0 | AB6: 12:17:59.99999999999616600 | AC6: 4.3 | AD6: 1.5
A7: Adam Ginning | C7: 0 | D7: D | E7: 2500 | F7: PHI | G7: @ COL | H7: 21:00:00.000 | I7: N | J7: 0.377 | K7: 165 | L7: 6.5 | M7: 3.25 | N7: 4.18 | Q7: 15:23:00.000000000004689600 | R7: 2.6 | S7: 1.67 | T7: 0 | U7: 0 | V7: 0 | W7: 100 | Y7: 68 | Z7: 0 | AA7: 0
A8: Adam Klapka | C8: 0 | D8: W | E8: 2500 | F8: CGY | G8: vs WSH | H8: 21:00:00.000 | I8: N | J8: 0.541 | K8: 85 | L8: 6 | M8: 2.8 | N8: 3 | O8: 4 | Q8: 10:35:59.99999999999872200 | R8: 3.9 | S8: 4.22 | T8: 12.36 | U8: 3.92 | V8: 3.92 | W8: 100 | Y8: 46 | Z8: 1.6 | AA8: 0 | AB8: 09:25:59.99999999999925675 | AC8: 4.3 | AD8: 1.7
A9: Adam Larsson | C9: 0 | D9: D | E9: 3500 | F9: SEA | G9: vs ANA | H9: 21:59:59.9999999999968050 | I9: Y | J9: 0.471 | K9: -89 | L9: 6 | M9: 3.14 | N9: 3 | O9: 1 | Q9: 21:50:59.99999999999872200 | R9: 7.1 | S9: 4.97 | T9: 18.56 | U9: 8.62 | V9: 8.62 | W9: 100 | Y9: 65 | Z9: 2.5 | AA9: 0 | AB9: 17:33:59.99999999999595075 | AC9: 1.3 | AD9: 0.4
A10: Adin Hill | C10: 0 | D10: G | E10: 7900 | F10: VGK | G10: @ TOR | H10: 18:59:59.9999999999968050 | I10: Y | J10: 0.417 | K10: -71.5 | L10: 6.5 | M10: 3.25 | N10: 3.2 | O10: confirm | Q10: PT49H47M0.000S | R10: 5.4 | S10: 6.71 | T10: 21.59 | U10: 8.17 | V10: 8.17 | W10: 100 | Y10: 38 | Z10: 1 | AA10: 0 | AB10: PT60H0M0.000S | AC10: 8.1 | AD10: 1
A11: Akira Schmid | C11: 0 | D11: G | E11: 7900 | F11: VGK | G11: @ TOR | H11: 18:59:59.9999999999968050 | I11: Y | J11: 0.417 | K11: -71.5 | L11: 6.5 | M11: 3.25 | N11: 3.2 | O11: unlikely | Q11: PT57H53M0.000S | R11: 10.8 | S11: 8.34 | T11: 0 | U11: 0 | V11: 0 | W11: 100 | Y11: 61 | Z11: 0 | AA11: 0 | AB11: 1899-12-30 | AC11: 0
A12: Aleksanteri Kaskimaki | C12: 0 | D12: C | E12: 2500 | F12: STL | G12: @ DAL | H12: 20:00:00.0000000000031950 | I12: N | J12: 0.514 | K12: 94.5 | L12: 5.5 | M12: 2.75 | N12: 3.07 | Q12: 11:17:59.99999999999936100 | R12: 3.8 | S12: 3.48 | T12: 0 | U12: 0 | V12: 0 | W12: 100 | Y12: 54 | Z12: 0 | AA12: 0
A13: Alex Killorn | C13: 0 | D13: W | E13: 3300 | F13: ANA | G13: @ SEA | H13: 21:59:59.9999999999968050 | I13: N | J13: 0.529 | K13: 89 | L13: 6 | M13: 3 | N13: 3.14 | O13: 1 | P13: 2 | Q13: 15:51:59.99999999999850675 | R13: 5.2 | S13: 4.7 | T13: 15.25 | U13: 5.85 | V13: 5.85 | W13: 100 | Y13: 55 | Z13: 1.8 | AA13: 0 | AB13: 15:16:59.99999999999637450 | AC13: 2.8 | AD13: 0.8
A14: Alex Nedeljkovic | C14: 0 | D14: G | E14: 8000 | F14: SJ | G14: vs NYR | H14: 21:59:59.9999999999968050 | I14: Y | J14: 0.446 | K14: -80.5 | L14: 6.5 | M14: 3.38 | N14: 3.25 | O14: confirm | Q14: PT57H13M0.000S | R14: 10.5 | S14: 9.77 | T14: 31.01 | U14: 11.47 | V14: 11.47 | W14: 100 | Y14: 53 | Z14: 1.4 | AA14: 0 | AB14: PT60H0M0.000S | AC14: 22.1 | AD14: 2.8
A15: Alex Ovechkin | C15: 0 | D15: W | E15: 7500 | F15: WSH | G15: @ CGY | H15: 21:00:00.000 | I15: Y | J15: 0.459 | K15: -85 | L15: 6 | M15: 3 | N15: 2.8 | O15: 3 | P15: 2 | Q15: 18:00:00.000 | R15: 10 | S15: 7.42 | T15: 26.25 | U15: 11.41 | V15: 11.41 | W15: 100 | Y15: 63 | Z15: 1.5 | AA15: 0 | AB15: 17:49:00.000000000002344800 | AC15: 20.5 | AD15: 2.7
A16: Alex Petrovic | C16: 0 | D16: D | E16: 2500 | F16: DAL | G16: vs STL | H16: 20:00:00.0000000000031950 | I16: Y | J16: 0.486 | K16: -94.5 | L16: 5.5 | M16: 3.07 | N16: 2.75 | Q16: 15:48:59.99999999999914575 | R16: 5.2 | S16: 4.6 | T16: 0 | U16: 0 | V16: 0 | W16: 100 | Y16: 56 | Z16: 0 | AA16: 0
A17: Alex Pietrangelo | B17: ! | C17: 0 | D17: D | E17: 2700 | F17: VGK | G17: @ TOR | H17: 18:59:59.9999999999968050 | I17: Y | J17: 0.417 | K17: -71.5 | L17: 6.5 | M17: 3.25 | N17: 3.2 | T17: 0 | U17: 0 | V17: 0 | W17: 100 | Y17: 0 | Z17: 0 | AA17: 0
A18: Alex Vlasic | C18: 0 | D18: D | E18: 2900 | F18: CHI | G18: vs TB | H18: 18:59:59.9999999999968050 | I18: N | J18: 0.386 | K18: 159 | L18: 6 | M18: 2.24 | N18: 3 | O18: 1 | Q18: 20:55:00.00000000000106275 | R18: 5.3 | S18: 4.25 | T18: 12.93 | U18: 4.43 | V18: 4.43 | W18: 100 | Y18: 60 | Z18: 1.5 | AA18: 0 | AB18: 23:42:00.00000000000383400 | AC18: 9.9 | AD18: 3.4
A19: Alex Wennberg | C19: 0 | D19: C | E19: 4000 | F19: SJ | G19: vs NYR | H19: 21:59:59.9999999999968050 | I19: Y | J19: 0.446 | K19: -80.5 | L19: 6.5 | M19: 3.38 | N19: 3.25 | O19: 2 | P19: 1 | Q19: 20:36:59.99999999999531175 | R19: 8.1 | S19: 7.1 | T19: 25.18 | U19: 10.98 | V19: 10.98 | W19: 100 | Y19: 56 | Z19: 2.7 | AA19: 0 | AB19: PT24H28M0.000S | AC19: 8.2 | AD19: 2.1
A20: Alexander Holtz | C20: 0 | D20: W | E20: 2500 | F20: VGK | G20: @ TOR | H20: 18:59:59.9999999999968050 | I20: Y | J20: 0.417 | K20: -71.5 | L20: 6.5 | M20: 3.25 | N20: 3.2 | O20: 4 | Q20: 11:55:00.00000000000106275 | R20: 4.4 | S20: 5.27 | T20: 15.72 | U20: 5.18 | V20: 5.18 | W20: 100 | Y20: 40 | Z20: 2.1 | AA20: 0 | AB20: 09:45:00.000 | AC20: 6.5 | AD20: 2.6
A21: Alexei Kolosov | C21: 0 | D21: G | E21: 7100 | F21: PHI | G21: @ COL | H21: 21:00:00.000 | I21: N | J21: 0.377 | K21: 165 | L21: 6.5 | M21: 3.25 | N21: 4.18 | O21: unlikely | Q21: PT30H0M0.000S | R21: 0.8 | S21: 7.56 | T21: 0 | U21: 0 | V21: 0 | W21: 100 | Y21: 0 | Z21: 0 | AA21: 0 | AB21: 1899-12-30 | AC21: 0
A22: Alexey Toropchenko | C22: 0 | D22: W | E22: 2500 | F22: STL | G22: @ DAL | H22: 20:00:00.0000000000031950 | I22: N | J22: 0.514 | K22: 94.5 | L22: 5.5 | M22: 2.75 | N22: 3.07 | O22: 4 | Q22: 12:17:59.99999999999616600 | R22: 4.4 | S22: 4.06 | T22: 12.89 | U22: 4.77 | V22: 4.77 | W22: 100 | Y22: 54 | Z22: 1.9 | AA22: 0 | AB22: 11:55:00.00000000000106275 | AC22: 1.3 | AD22: 0.5
A23: Alexis Lafreniere | C23: 0 | D23: W | E23: 4000 | F23: NYR | G23: @ SJ | H23: 21:59:59.9999999999968050 | I23: N | J23: 0.554 | K23: 80.5 | L23: 6.5 | M23: 3.25 | N23: 3.38 | O23: 1 | P23: 2 | Q23: 17:11:00.00000000000085425 | R23: 7.3 | S23: 6.45 | T23: 21.47 | U23: 8.57 | V23: 8.57 | W23: 100 | Y23: 56 | Z23: 2.1 | AA23: 0 | AB23: 14:19:59.99999999999893725 | AC23: 1.5 | AD23: 0.4
A24: Aliaksei Protas | C24: 0 | D24: W | E24: 5100 | F24: WSH | G24: @ CGY | H24: 21:00:00.000 | I24: Y | J24: 0.459 | K24: -85 | L24: 6 | M24: 3 | N24: 2.8 | O24: 2 | Q24: 18:18:59.99999999999595075 | R24: 8.8 | S24: 7.26 | T24: 24.86 | U24: 10.34 | V24: 10.34 | W24: 100 | Y24: 59 | Z24: 2 | AA24: 0 | AB24: 19:12:00.00000000000383400 | AC24: 15.6 | AD24: 3.1
A25: Andre Burakovsky | C25: 0 | D25: W | E25: 3500 | F25: CHI | G25: vs TB | H25: 18:59:59.9999999999968050 | I25: N | J25: 0.386 | K25: 159 | L25: 6 | M25: 2.24 | N25: 3 | O25: 2 | P25: 1 | Q25: 17:29:59.9999999999968050 | R25: 7.1 | S25: 6.41 | T25: 18.36 | U25: 5.54 | V25: 5.54 | W25: 100 | Y25: 55 | Z25: 1.6 | AA25: 0 | AB25: 21:26:00.00000000000404925 | AC25: 5.8 | AD25: 1.7
A26: Andrei Vasilevskiy | C26: 0 | D26: G | E26: 8400 | F26: TB | G26: @ CHI | H26: 18:59:59.9999999999968050 | I26: Y | J26: 0.614 | K26: -159 | L26: 6 | M26: 3 | N26: 2.24 | O26: confirm | Q26: PT58H56M0.000S | R26: 12.5 | S26: 8.48 | T26: 28.91 | U26: 11.95 | V26: 11.95 | W26: 100 | Y26: 66 | Z26: 1.4 | AA26: 0 | AB26: PT65H0M0.000S | AC26: 14.4 | AD26: 1.7
A27: Angus Crookshank | C27: 0 | D27: W | E27: 2500 | F27: NJ | G27: @ VAN | H27: 21:59:59.9999999999968050 | I27: Y | J27: 0.472 | K27: -89.5 | L27: 6 | M27: 3 | N27: 2.77 | Q27: 08:35:00.00000000000053475 | R27: 3 | S27: 3.94 | T27: 0 | U27: 0 | V27: 0 | W27: 100 | Y27: 34 | Z27: 0 | AA27: 0
A28: Anthony Beauvillier | C28: 0 | D28: W | E28: 3600 | F28: WSH | G28: @ CGY | H28: 21:00:00.000 | I28: Y | J28: 0.459 | K28: -85 | L28: 6 | M28: 3 | N28: 2.8 | O28: 4 | Q28: 15:47:59.99999999999936100 | R28: 6 | S28: 4.54 | T28: 16.24 | U28: 7.16 | V28: 7.16 | W28: 100 | Y28: 62 | Z28: 2 | AA28: 0 | AB28: 13:47:59.99999999999616600 | AC28: 3 | AD28: 0.8
A29: Anthony Cirelli | C29: 0 | D29: C | E29: 5400 | F29: TB | G29: @ CHI | H29: 18:59:59.9999999999968050 | I29: Y | J29: 0.614 | K29: -159 | L29: 6 | M29: 3 | N29: 2.24 | O29: 1 | P29: 2 | Q29: 17:32:59.99999999999616600 | R29: 8.2 | S29: 6.45 | T29: 21.42 | U29: 8.52 | V29: 8.52 | W29: 100 | Y29: 61 | Z29: 1.6 | AA29: 0 | AB29: 19:21:00.00000000000191700 | AC29: 9.3 | AD29: 1.7
A30: Anthony Stolarz | C30: 0 | D30: G | E30: 7300 | F30: TOR | G30: vs VGK | H30: 18:59:59.9999999999968050 | I30: N | J30: 0.583 | K30: 71.5 | L30: 6.5 | M30: 3.2 | N30: 3.25 | O30: confirm | Q30: PT54H3M0.000S | R30: 9.2 | S30: 9.36 | T30: 30.56 | U30: 11.84 | V30: 11.84 | W30: 100 | Y30: 49 | Z30: 1.6 | AA30: 0 | AB30: PT58H20M0.000S | AC30: 0
A31: Anton Blidh | C31: 0 | D31: W | E31: 2500 | F31: NYR | G31: @ SJ | H31: 21:59:59.9999999999968050 | I31: N | J31: 0.554 | K31: 80.5 | L31: 6.5 | M31: 3.25 | N31: 3.38 | O31: 4 | Q31: 07:47:00.00000000000117375 | R31: 0.8 | S31: 0.75 | T31: 5.98 | U31: 4.48 | V31: 4.48 | W31: 100 | Y31: 0 | Z31: 1.8 | AA31: 0 | AB31: 06:14:00.00000000000181275 | AC31: 9.5 | AD31: 3.8
A32: Arseny Gritsyuk | C32: 0 | D32: W | E32: 3300 | F32: NJ | G32: @ VAN | H32: 21:59:59.9999999999968050 | I32: Y | J32: 0.472 | K32: -89.5 | L32: 6 | M32: 3 | N32: 2.77 | O32: 3 | Q32: 14:57:00.00000000000063900 | R32: 6.8 | S32: 6.14 | T32: 20.09 | U32: 7.81 | V32: 7.81 | W32: 100 | Y32: 55 | Z32: 2.4 | AA32: 0 | AB32: 13:14:00.00000000000341025 | AC32: 5 | AD32: 1.5
A33: Arshdeep Bains | C33: 0 | D33: W | E33: 2500 | F33: VAN | G33: vs NJ | H33: 21:59:59.9999999999968050 | I33: N | J33: 0.528 | K33: 89.5 | L33: 6 | M33: 2.77 | N33: 3 | Q33: 09:23:59.99999999999968050 | R33: 2.4 | S33: 3.25 | T33: 0 | U33: 0 | V33: 0 | W33: 100 | Y33: 32 | Z33: 0 | AA33: 0
A34: Artemi Panarin | C34: 0 | D34: W | E34: 8300 | F34: NYR | G34: @ SJ | H34: 21:59:59.9999999999968050 | I34: N | J34: 0.554 | K34: 80.5 | L34: 6.5 | M34: 3.25 | N34: 3.38 | O34: 1 | P34: 1 | Q34: 20:47:00.00000000000277125 | R34: 12.9 | S34: 9.68 | T34: 36.47 | U34: 17.11 | V34: 17.11 | W34: 100 | Y34: 62 | Z34: 2.1 | AA34: 0 | AB34: 21:09:59.99999999999786775 | AC34: 4.5 | AD34: 0.5
A35: Artturi Lehkonen | C35: 0 | D35: W | E35: 5700 | F35: COL | G35: vs PHI | H35: 21:00:00.000 | I35: Y | J35: 0.623 | K35: -165 | L35: 6.5 | M35: 4.18 | N35: 3.25 | O35: 2 | P35: 2 | Q35: 19:23:00.00000000000149325 | R35: 9.3 | S35: 6.26 | T35: 24.87 | U35: 12.35 | V35: 12.35 | W35: 100 | Y35: 66 | Z35: 2.2 | AA35: 0 | AB35: 15:16:59.99999999999637450 | AC35: 0
A36: Artyom Levshunov | C36: 0 | D36: D | E36: 3800 | F36: CHI | G36: vs TB | H36: 18:59:59.9999999999968050 | I36: N | J36: 0.386 | K36: 159 | L36: 6 | M36: 2.24 | N36: 3 | O36: 2 | P36: 1 | Q36: 19:00:59.99999999999658975 | R36: 5.7 | S36: 4.39 | T36: 13.66 | U36: 4.88 | V36: 4.88 | W36: 100 | Y36: 61 | Z36: 1.3 | AA36: 0 | AB36: 21:58:59.99999999999701350 | AC36: 0
A37: Arvid Soderblom | C37: 0 | D37: G | E37: 7000 | F37: CHI | G37: vs TB | H37: 18:59:59.9999999999968050 | I37: N | J37: 0.386 | K37: 159 | L37: 6 | M37: 2.24 | N37: 3 | O37: confirm | Q37: PT57H38M0.000S | R37: 6.5 | S37: 10.7 | T37: 28.75 | U37: 7.35 | V37: 7.35 | W37: 100 | Y37: 18 | Z37: 1.1 | AA37: 0 | AB37: PT65H0M0.000S | AC37: 19.5 | AD37: 2.8
A38: Auston Matthews | C38: 0 | D38: C | E38: 9700 | F38: TOR | G38: vs VGK | H38: 18:59:59.9999999999968050 | I38: N | J38: 0.583 | K38: 71.5 | L38: 6.5 | M38: 3.2 | N38: 3.25 | O38: 1 | P38: 1 | Q38: 20:47:00.00000000000277125 | R38: 15.9 | S38: 9.99 | T38: 38.96 | U38: 18.98 | V38: 18.98 | W38: 100 | Y38: 69 | Z38: 2 | AA38: 0 | AB38: 23:29:59.9999999999968050 | AC38: 4.5 | AD38: 0.5
A39: Barclay Goodrow | C39: 0 | D39: W | E39: 2500 | F39: SJ | G39: vs NYR | H39: 21:59:59.9999999999968050 | I39: Y | J39: 0.446 | K39: -80.5 | L39: 6.5 | M39: 3.38 | N39: 3.25 | O39: 4 | Q39: 11:37:00.00000000000010425 | R39: 3.8 | S39: 5.28 | T39: 16.37 | U39: 5.81 | V39: 5.81 | W39: 100 | Y39: 31 | Z39: 2.3 | AA39: 0 | AB39: 07:30:59.999999999999786775 | AC39: 2.6 | AD39: 1
A40: Beckett Sennecke | C40: 0 | D40: W | E40: 5200 | F40: ANA | G40: @ SEA | H40: 21:59:59.9999999999968050 | I40: N | J40: 0.529 | K40: 89 | L40: 6 | M40: 3 | N40: 3.14 | O40: 1 | P40: 1 | Q40: 17:02:00.00000000000277125 | R40: 8.9 | S40: 7.23 | T40: 25.3 | U40: 10.84 | V40: 10.84 | W40: 100 | Y40: 59 | Z40: 2.1 | AA40: 0 | AB40: 13:54:00.00000000000447975 | AC40: 1.5 | AD40: 0.3
A41: Ben Hutton | C41: 0 | D41: D | E41: 2700 | F41: VGK | G41: @ TOR | H41: 18:59:59.9999999999968050 | I41: Y | J41: 0.417 | K41: -71.5 | L41: 6.5 | M41: 3.25 | N41: 3.2 | O41: 3 | Q41: 14:50:00.00000000000213225 | R41: 5.6 | S41: 4.8 | T41: 16.32 | U41: 6.72 | V41: 6.72 | W41: 100 | Y41: 57 | Z41: 2.5 | AA41: 0 | AB41: 14:26:59.999999999997441975 | AC41: 0
A42: Ben Meyers | C42: 0 | D42: C | E42: 2500 | F42: SEA | G42: vs ANA | H42: 21:59:59.9999999999968050 | I42: Y | J42: 0.471 | K42: -89 | L42: 6 | M42: 3.14 | N42: 3 | Q42: 11:37:59.999999999999893725 | R42: 4.7 | S42: 5.53 | T42: 0 | U42: 0 | V42: 0 | W42: 100 | Y42: 41 | Z42: 0 | AA42: 0
A43: Berkly Catton | C43: 0 | D43: W | E43: 2900 | F43: SEA | G43: vs ANA | H43: 21:59:59.9999999999968050 | I43: Y | J43: 0.471 | K43: -89 | L43: 6 | M43: 3.14 | N43: 3 | O43: 3 | Q43: 12:48:59.99999999999914575 | R43: 4.1 | S43: 4.23 | T43: 13.26 | U43: 4.8 | V43: 4.8 | W43: 100 | Y43: 48 | Z43: 1.7 | AA43: 0 | AB43: 13:36:59.99999999999850675 | AC43: 1.5 | AD43: 0.5
A44: Blake Coleman | C44: 0 | D44: W | E44: 3900 | F44: CGY | G44: vs WSH | H44: 21:00:00.000 | I44: N | J44: 0.541 | K44: 85 | L44: 6 | M44: 2.8 | N44: 3 | Q44: 16:57:00.00000000000383400 | R44: 8.1 | S44: 6.14 | T44: 0 | U44: 0 | V44: 0 | W44: 100 | Y44: 62 | Z44: 0 | AA44: 0
A45: Bobby Brink | C45: 0 | D45: W | E45: 3600 | F45: PHI | G45: @ COL | H45: 21:00:00.000 | I45: N | J45: 0.377 | K45: 165 | L45: 6.5 | M45: 3.25 | N45: 4.18 | O45: 3 | P45: 1 | Q45: 15:29:00.00000000000341025 | R45: 6.8 | S45: 5.97 | T45: 20.63 | U45: 8.69 | V45: 8.69 | W45: 100 | Y45: 56 | Z45: 2.4 | AA45: 0 | AB45: 13:13:00.00000000000362550 | AC45: 11.5 | AD45: 3.2
A46: Bobby McMann | C46: 0 | D46: W | E46: 4200 | F46: TOR | G46: vs VGK | H46: 18:59:59.9999999999968050 | I46: N | J46: 0.583 | K46: 71.5 | L46: 6.5 | M46: 3.2 | N46: 3.25 | O46: 1 | P46: 2 | Q46: 15:04:59.99999999999893725 | R46: 7.3 | S46: 6.59 | T46: 22.76 | U46: 9.58 | V46: 9.58 | W46: 100 | Y46: 55 | Z46: 2.3 | AA46: 0 | AB46: 17:18:59.99999999999914575 | AC46: 14.5 | AD46: 3.5
A47: Bogdan Trineyev | C47: 0 | D47: W | E47: 2500 | F47: WSH | G47: @ CGY | H47: 21:00:00.000 | I47: Y | J47: 0.459 | K47: -85 | L47: 6 | M47: 3 | N47: 2.8 | Q47: 10:30:59.999999999999786775 | R47: 2.1 | S47: 0.75 | T47: 0 | U47: 0 | V47: 0 | W47: 100 | Y47: 0 | Z47: 0 | AA47: 0
A48: Boris Katchouk | C48: 0 | D48: W | E48: 2500 | F48: TB | G48: @ CHI | H48: 18:59:59.9999999999968050 | I48: Y | J48: 0.614 | K48: -159 | L48: 6 | M48: 3 | N48: 2.24 | Q48: 14:21:59.99999999999850675 | R48: 1.4 | S48: 1.41 | T48: 0 | U48: 0 | V48: 0 | W48: 100 | Y48: 50 | Z48: 0 | AA48: 0
A49: Braden Schneider | C49: 0 | D49: D | E49: 3100 | F49: NYR | G49: @ SJ | H49: 21:59:59.9999999999968050 | I49: N | J49: 0.554 | K49: 80.5 | L49: 6.5 | M49: 3.25 | N49: 3.38 | O49: 1 | Q49: 20:07:00.00000000000170850 | R49: 5.7 | S49: 4.11 | T49: 15.39 | U49: 7.17 | V49: 7.17 | W49: 100 | Y49: 64 | Z49: 2.3 | AA49: 0 | AB49: 22:45:59.99999999999658975 | AC49: 2.6 | AD49: 0.8
A50: Braeden Bowman | C50: 0 | D50: W | E50: 2600 | F50: VGK | G50: @ TOR | H50: 18:59:59.9999999999968050 | I50: Y | J50: 0.417 | K50: -71.5 | L50: 6.5 | M50: 3.25 | N50: 3.2 | O50: 3 | P50: 2 | Q50: 14:13:00.00000000000042375 | R50: 6 | S50: 5.21 | T50: 17.62 | U50: 7.2 | V50: 7.2 | W50: 100 | Y50: 57 | Z50: 2.8 | AA50: 0 | AB50: 10:17:59.99999999999776350 | AC50: 11.5 | AD50: 4.4
A51: Braeden Cootes | C51: 0 | D51: C | E51: 2500 | F51: VAN | G51: vs NJ | H51: 21:59:59.9999999999968050 | I51: N | J51: 0.528 | K51: 89.5 | L51: 6 | M51: 2.77 | N51: 3 | Q51: 11:22:59.99999999999829150 | R51: 2.3 | S51: 3.23 | T51: 0 | U51: 0 | V51: 0 | W51: 100 | Y51: 30 | Z51: 0 | AA51: 0
A52: Brandon Carlo | C52: 0 | D52: D | E52: 2700 | F52: TOR | G52: vs VGK | H52: 18:59:59.9999999999968050 | I52: N | J52: 0.583 | K52: 71.5 | L52: 6.5 | M52: 3.2 | N52: 3.25 | O52: 2 | Q52: 19:37:59.99999999999829150 | R52: 6.2 | S52: 4.04 | T52: 15.56 | U52: 7.48 | V52: 7.48 | W52: 100 | Y52: 67 | Z52: 2.8 | AA52: 0 | AB52: 15:50:59.99999999999872200 | AC52: 0
A53: Brandon Duhaime | C53: 0 | D53: W | E53: 2500 | F53: WSH | G53: @ CGY | H53: 21:00:00.000 | I53: Y | J53: 0.459 | K53: -85 | L53: 6 | M53: 3 | N53: 2.8 | O53: 4 | Q53: 11:15:59.999999999999786775 | R53: 2.8 | S53: 4.14 | T53: 10.92 | U53: 2.64 | V53: 2.64 | W53: 100 | Y53: 26 | Z53: 1.1 | AA53: 0 | AB53: 09:14:00.00000000000181275 | AC53: 2.6 | AD53: 1
A54: Brandon Hagel | C54: 0 | D54: W | E54: 7700 | F54: TB | G54: @ CHI | H54: 18:59:59.9999999999968050 | I54: Y | J54: 0.614 | K54: -159 | L54: 6 | M54: 3 | N54: 2.24 | O54: 1 | P54: 1 | Q54: 18:54:59.99999999999786775 | R54: 13.5 | S54: 10.94 | T54: 39.21 | U54: 17.33 | V54: 17.33 | W54: 100 | Y54: 59 | Z54: 2.3 | AA54: 0 | AB54: 23:45:00.0000000000031950 | AC54: 8 | AD54: 1
A55: Brandon Montour | C55: 0 | D55: D | E55: 5400 | F55: SEA | G55: vs ANA | H55: 21:59:59.9999999999968050 | I55: Y | J55: 0.471 | K55: -89 | L55: 6 | M55: 3.14 | N55: 3 | O55: 2 | P55: 2 | Q55: 22:02:59.99999999999616600 | R55: 10 | S55: 6.49 | T55: 24.48 | U55: 11.5 | V55: 11.5 | W55: 100 | Y55: 68 | Z55: 2.1 | AA55: 0 | AB55: PT27H54M0.000S | AC55: 5.6 | AD55: 1
A56: Brandon Saad | C56: 0 | D56: W | E56: 2500 | F56: VGK | G56: @ TOR | H56: 18:59:59.9999999999968050 | I56: Y | J56: 0.417 | K56: -71.5 | L56: 6.5 | M56: 3.25 | N56: 3.2 | Q56: 13:51:59.99999999999531175 | R56: 4.3 | S56: 3.79 | T56: 0 | U56: 0 | V56: 0 | W56: 100 | Y56: 56 | Z56: 0 | AA56: 0
A57: Brayden McNabb | B57: ! | C57: 0 | D57: D | E57: 3500 | F57: VGK | G57: @ TOR | H57: 18:59:59.9999999999968050 | I57: Y | J57: 0.417 | K57: -71.5 | L57: 6.5 | M57: 3.25 | N57: 3.2 | Q57: 20:49:00.000000000002344800 | R57: 6.8 | S57: 4.81 | T57: 0 | U57: 0 | V57: 0 | W57: 100 | Y57: 65 | Z57: 0 | AA57: 0
A58: Brayden Pachal | C58: 0 | D58: D | E58: 2500 | F58: CGY | G58: vs WSH | H58: 21:00:00.000 | I58: N | J58: 0.541 | K58: 85 | L58: 6 | M58: 2.8 | N58: 3 | Q58: 13:23:00.00000000000149325 | R58: 3 | S58: 2.97 | T58: 0 | U58: 0 | V58: 0 | W58: 100 | Y58: 51 | Z58: 0 | AA58: 0 | AB58: 11:41:59.99999999999904150 | AC58: 0
A59: Brayden Point | C59: 0 | D59: C | E59: 6200 | F59: TB | G59: @ CHI | H59: 18:59:59.9999999999968050 | I59: Y | J59: 0.614 | K59: -159 | L59: 6 | M59: 3 | N59: 2.24 | Q59: 18:00:59.999999999999786775 | R59: 9.5 | S59: 6.6 | T59: 0 | U59: 0 | V59: 0 | W59: 100 | Y59: 65 | Z59: 0 | AA59: 0
A60: Brayden Schenn | C60: 0 | D60: C | E60: 3200 | F60: STL | G60: @ DAL | H60: 20:00:00.0000000000031950 | I60: N | J60: 0.514 | K60: 94.5 | L60: 5.5 | M60: 2.75 | N60: 3.07 | O60: 1 | P60: 2 | Q60: 16:34:59.99999999999893725 | R60: 5.3 | S60: 5.82 | T60: 17.82 | U60: 6.18 | V60: 6.18 | W60: 100 | Y60: 45 | Z60: 1.9 | AA60: 0 | AB60: 16:23:00.00000000000149325 | AC60: 5.8 | AD60: 1.8
A61: Brenden Dillon | C61: 0 | D61: D | E61: 2500 | F61: NJ | G61: @ VAN | H61: 21:59:59.9999999999968050 | I61: Y | J61: 0.472 | K61: -89.5 | L61: 6 | M61: 3 | N61: 2.77 | O61: 2 | Q61: 18:09:59.99999999999786775 | R61: 4.8 | S61: 4.52 | T61: 13.45 | U61: 4.41 | V61: 4.41 | W61: 100 | Y61: 53 | Z61: 1.8 | AA61: 0 | AB61: 20:22:59.99999999999829150 | AC61: 2.6 | AD61: 1
A62: Brennan Othmann | C62: 0 | D62: W | E62: 2500 | F62: NYR | G62: @ SJ | H62: 21:59:59.9999999999968050 | I62: N | J62: 0.554 | K62: 80.5 | L62: 6.5 | M62: 3.25 | N62: 3.38 | O62: 3 | Q62: 09:35:00.00000000000213225 | R62: 2.8 | S62: 2.88 | T62: 9.54 | U62: 3.78 | V62: 3.78 | W62: 100 | Y62: 49 | Z62: 1.5 | AA62: 0 | AB62: 09:00:59.999999999999786775 | AC62: 3 | AD62: 1.2
A63: Brent Burns | C63: 0 | D63: D | E63: 4600 | F63: COL | G63: vs PHI | H63: 21:00:00.000 | I63: Y | J63: 0.623 | K63: -165 | L63: 6.5 | M63: 4.18 | N63: 3.25 | O63: 2 | P63: 2 | Q63: 19:24:00.00000000000127800 | R63: 8.7 | S63: 5.09 | T63: 24.47 | U63: 14.29 | V63: 14.29 | W63: 100 | Y63: 71 | Z63: 3.1 | AA63: 0 | AB63: 17:54:00.00000000000127800 | AC63: 1.5 | AD63: 0.3
A64: Brett Berard | C64: 0 | D64: W | E64: 2500 | F64: NYR | G64: @ SJ | H64: 21:59:59.9999999999968050 | I64: N | J64: 0.554 | K64: 80.5 | L64: 6.5 | M64: 3.25 | N64: 3.38 | Q64: 10:50:00.00000000000053475 | R64: 2.3 | S64: 1.95 | T64: 0 | U64: 0 | V64: 0 | W64: 100 | Y64: 58 | Z64: 0 | AA64: 0
A65: Brett Howden | B65: ! | C65: 0 | D65: W | E65: 2700 | F65: VGK | G65: @ TOR | H65: 18:59:59.9999999999968050 | I65: Y | J65: 0.417 | K65: -71.5 | L65: 6.5 | M65: 3.25 | N65: 3.2 | Q65: 14:50:00.00000000000213225 | R65: 4.8 | S65: 5 | T65: 0 | U65: 0 | V65: 0 | W65: 100 | Y65: 48 | Z65: 0 | AA65: 0
A66: Brett Leason | C66: 0 | D66: W | E66: 2500 | F66: WSH | G66: @ CGY | H66: 21:00:00.000 | I66: Y | J66: 0.459 | K66: -85 | L66: 6 | M66: 3 | N66: 2.8 | Q66: 08:34:00.00000000000074325 | R66: 0.3 | S66: 0.56 | T66: 0 | U66: 0 | V66: 0 | W66: 100 | Y66: 7 | Z66: 0 | AA66: 0
A67: Brett Pesce | C67: 0 | D67: D | E67: 3100 | F67: NJ | G67: @ VAN | H67: 21:59:59.9999999999968050 | I67: Y | J67: 0.472 | K67: -89.5 | L67: 6 | M67: 3 | N67: 2.77 | O67: 1 | Q67: 20:08:00.00000000000149325 | R67: 7.5 | S67: 6.44 | T67: 21.46 | U67: 8.58 | V67: 8.58 | W67: 100 | Y67: 57 | Z67: 2.8 | AA67: 0 | AB67: 23:56:00.00000000000085425 | AC67: 1.3 | AD67: 0.4
A68: Brian Halonen | C68: 0 | D68: W | E68: 2500 | F68: NJ | G68: @ VAN | H68: 21:59:59.9999999999968050 | I68: Y | J68: 0.472 | K68: -89.5 | L68: 6 | M68: 3 | N68: 2.77 | Q68: 07:30:00.000 | R68: 1.9 | S68: 3.39 | T68: 0 | U68: 0 | V68: 0 | W68: 100 | Y68: 11 | Z68: 0 | AA68: 0
A69: Brock Boeser | C69: 0 | D69: W | E69: 4400 | F69: VAN | G69: vs NJ | H69: 21:59:59.9999999999968050 | I69: N | J69: 0.528 | K69: 89.5 | L69: 6 | M69: 2.77 | N69: 3 | O69: 2 | P69: 1 | Q69: 19:25:00.00000000000106275 | R69: 7.9 | S69: 7.25 | T69: 20.75 | U69: 6.25 | V69: 6.25 | W69: 100 | Y69: 54 | Z69: 1.4 | AA69: 0 | AB69: 20:25:59.9999999999976525 | AC69: 11.5 | AD69: 2.6
A70: Brock Nelson | C70: 0 | D70: C | E70: 7000 | F70: COL | G70: vs PHI | H70: 21:00:00.000 | I70: Y | J70: 0.623 | K70: -165 | L70: 6.5 | M70: 4.18 | N70: 3.25 | O70: 2 | P70: 1 | Q70: 19:01:59.99999999999637450 | R70: 11.2 | S70: 8.42 | T70: 39.58 | U70: 22.74 | V70: 22.74 | W70: 100 | Y70: 62 | Z70: 3.2 | AA70: 0 | AB70: 22:37:59.99999999999829150 | AC70: 4.1 | AD70: 0.6
A71: Cale Fleury | C71: 0 | D71: D | E71: 2500 | F71: SEA | G71: vs ANA | H71: 21:59:59.9999999999968050 | I71: Y | J71: 0.471 | K71: -89 | L71: 6 | M71: 3.14 | N71: 3 | Q71: 17:35:59.99999999999552025 | R71: 4.3 | S71: 3.54 | T71: 0 | U71: 0 | V71: 0 | W71: 100 | Y71: 59 | Z71: 0 | AA71: 0
A72: Cale Makar | C72: 0 | D72: D | E72: 8200 | F72: COL | G72: vs PHI | H72: 21:00:00.000 | I72: Y | J72: 0.623 | K72: -165 | L72: 6.5 | M72: 4.18 | N72: 3.25 | O72: 1 | P72: 1 | Q72: PT25H6M0.000S | R72: 13.9 | S72: 8.82 | T72: 39.18 | U72: 21.54 | V72: 21.54 | W72: 100 | Y72: 68 | Z72: 2.6 | AA72: 0 | AB72: PT26H21M0.000S | AC72: 12.8 | AD72: 1.6
A73: Calle Jarnkrok | C73: 0 | D73: W | E73: 2500 | F73: TOR | G73: vs VGK | H73: 18:59:59.9999999999968050 | I73: N | J73: 0.583 | K73: 71.5 | L73: 6.5 | M73: 3.2 | N73: 3.25 | O73: 4 | Q73: 11:52:00.00000000000170850 | R73: 3.4 | S73: 3.78 | T73: 11.27 | U73: 3.71 | V73: 3.71 | W73: 100 | Y73: 44 | Z73: 1.5 | AA73: 0 | AB73: 08:41:59.99999999999904150 | AC73: 1.5 | AD73: 0.6
A74: Cam Fowler | C74: 0 | D74: D | E74: 3000 | F74: STL | G74: @ DAL | H74: 20:00:00.0000000000031950 | I74: N | J74: 0.514 | K74: 94.5 | L74: 5.5 | M74: 2.75 | N74: 3.07 | O74: 3 | Q74: 21:32:00.00000000000277125 | R74: 5 | S74: 4.06 | T74: 12.69 | U74: 4.57 | V74: 4.57 | W74: 100 | Y74: 59 | Z74: 1.5 | AA74: 0 | AB74: 19:31:59.99999999999957625 | AC74: 6.3 | AD74: 2.1
A75: Cam York | C75: 0 | D75: D | E75: 3900 | F75: PHI | G75: @ COL | H75: 21:00:00.000 | I75: N | J75: 0.377 | K75: 165 | L75: 6.5 | M75: 3.25 | N75: 4.18 | O75: 1 | P75: 2 | Q75: 22:59:00.00000000000341025 | R75: 8.4 | S75: 6.34 | T75: 22.76 | U75: 10.08 | V75: 10.08 | W75: 100 | Y75: 62 | Z75: 2.6 | AA75: 0 | AB75: 21:33:00.00000000000255600 | AC75: 9.1 | AD75: 2.3
A76: Carey Price | C76: 0 | D76: G | E76: 7800 | F76: SJ | G76: vs NYR | H76: 21:59:59.9999999999968050 | I76: Y | J76: 0.446 | K76: -80.5 | L76: 6.5 | M76: 3.38 | N76: 3.25 | O76: unlikely | T76: 0 | U76: 0 | V76: 0 | W76: 100 | Y76: 0 | Z76: 0 | AA76: 0
A77: Carl Grundstrom | C77: 0 | D77: W | E77: 2800 | F77: PHI | G77: @ COL | H77: 21:00:00.000 | I77: N | J77: 0.377 | K77: 165 | L77: 6.5 | M77: 3.25 | N77: 4.18 | Q77: 12:48:59.99999999999914575 | R77: 5.6 | S77: 5.55 | T77: 0 | U77: 0 | V77: 0 | W77: 100 | Y77: 50 | Z77: 0 | AA77: 0 | AB77: 11:30:00.0000000000015975 | AC77: 0
A78: Carl Lindbom | C78: 0 | D78: G | E78: 6500 | F78: VGK | G78: @ TOR | H78: 18:59:59.9999999999968050 | I78: Y | J78: 0.417 | K78: -71.5 | L78: 6.5 | M78: 3.25 | N78: 3.2 | O78: unlikely | Q78: PT60H5M0.000S | R78: 5.9 | S78: 5.1 | T78: 0 | U78: 0 | V78: 0 | W78: 100 | Y78: 57 | Z78: 0 | AA78: 0
A79: Carson Soucy | C79: 0 | D79: D | E79: 2500 | F79: NYR | G79: @ SJ | H79: 21:59:59.9999999999968050 | I79: N | J79: 0.554 | K79: 80.5 | L79: 6.5 | M79: 3.25 | N79: 3.38 | O79: 2 | Q79: 17:26:59.999999999997441975 | R79: 5.2 | S79: 4.44 | T79: 15.49 | U79: 6.61 | V79: 6.61 | W79: 100 | Y79: 57 | Z79: 2.6 | AA79: 0 | AB79: 12:49:59.99999999999893725 | AC79: 0
A80: Carter Hart | C80: 0 | D80: G | E80: 7700 | F80: VGK | G80: @ TOR | H80: 18:59:59.9999999999968050 | I80: Y | J80: 0.417 | K80: -71.5 | L80: 6.5 | M80: 3.25 | N80: 3.2 | O80: unlikely | Q80: PT54H56M0.000S | R80: 6.4 | S80: 9.72 | T80: 0 | U80: 0 | V80: 0 | W80: 100 | Y80: 24 | Z80: 0 | AA80: 0
A81: Casey Desmith | C81: 0 | D81: G | E81: 8200 | F81: DAL | G81: vs STL | H81: 20:00:00.0000000000031950 | I81: Y | J81: 0.486 | K81: -94.5 | L81: 5.5 | M81: 3.07 | N81: 2.75 | O81: unlikely | Q81: PT58H59M0.000S | R81: 12.6 | S81: 7.69 | T81: 0 | U81: 0 | V81: 0 | W81: 100 | Y81: 69 | Z81: 0 | AA81: 0 | AB81: 1899-12-30 | AC81: 0
A82: Chandler Stephenson | C82: 0 | D82: C | E82: 3900 | F82: SEA | G82: vs ANA | H82: 21:59:59.9999999999968050 | I82: Y | J82: 0.471 | K82: -89 | L82: 6 | M82: 3.14 | N82: 3 | O82: 3 | P82: 1 | Q82: 19:46:59.99999999999637450 | R82: 7.1 | S82: 6.08 | T82: 20.89 | U82: 8.73 | V82: 8.73 | W82: 100 | Y82: 57 | Z82: 2.2 | AA82: 0 | AB82: 15:53:59.99999999999808300 | AC82: 1.3 | AD82: 0.3
A83: Charle-Edouard D'Astous | C83: 0 | D83: D | E83: 3000 | F83: TB | G83: @ CHI | H83: 18:59:59.9999999999968050 | I83: Y | J83: 0.614 | K83: -159 | L83: 6 | M83: 3 | N83: 2.24 | O83: 2 | P83: 2 | Q83: 19:28:00.00000000000042375 | R83: 6 | S83: 4.86 | T83: 16.84 | U83: 7.12 | V83: 7.12 | W83: 100 | Y83: 60 | Z83: 2.4 | AA83: 0 | AB83: 20:51:00.00000000000191700 | AC83: 1.3 | AD83: 0.4
A84: Charlie Lindgren | C84: 0 | D84: G | E84: 7800 | F84: WSH | G84: @ CGY | H84: 21:00:00.000 | I84: Y | J84: 0.459 | K84: -85 | L84: 6 | M84: 3 | N84: 2.8 | O84: unlikely | Q84: PT58H52M0.000S | R84: 10.1 | S84: 10.31 | T84: 0 | U84: 0 | V84: 0 | W84: 100 | Y84: 49 | Z84: 0 | AA84: 0 | AB84: 1899-12-30 | AC84: 0
A85: Chris Kreider | C85: 0 | D85: W | E85: 3700 | F85: ANA | G85: @ SEA | H85: 21:59:59.9999999999968050 | I85: N | J85: 0.529 | K85: 89 | L85: 6 | M85: 3 | N85: 3.14 | O85: 2 | P85: 1 | Q85: 17:01:00.00000000000298650 | R85: 7.5 | S85: 7.08 | T85: 20.57 | U85: 6.41 | V85: 6.41 | W85: 100 | Y85: 53 | Z85: 1.7 | AA85: 0 | AB85: 16:47:59.99999999999616600 | AC85: 10 | AD85: 2.7
A86: Chris Tanev | C86: 0 | D86: D | E86: 2500 | F86: TOR | G86: vs VGK | H86: 18:59:59.9999999999968050 | I86: N | J86: 0.583 | K86: 71.5 | L86: 6.5 | M86: 3.2 | N86: 3.25 | Q86: 17:58:00.00000000000042375 | R86: 4.7 | S86: 3.02 | T86: 0 | U86: 0 | V86: 0 | W86: 100 | Y86: 68 | Z86: 0 | AA86: 0
A87: Christian Dvorak | C87: 0 | D87: C | E87: 4900 | F87: PHI | G87: @ COL | H87: 21:00:00.000 | I87: N | J87: 0.377 | K87: 165 | L87: 6.5 | M87: 3.25 | N87: 4.18 | O87: 1 | P87: 1 | Q87: 17:35:59.99999999999552025 | R87: 8.4 | S87: 7.24 | T87: 24.89 | U87: 10.41 | V87: 10.41 | W87: 100 | Y87: 57 | Z87: 2.1 | AA87: 0 | AB87: 20:48:00.00000000000255600 | AC87: 5.8 | AD87: 1.2
A88: Cody Glass | C88: 0 | D88: C | E88: 3100 | F88: NJ | G88: @ VAN | H88: 21:59:59.9999999999968050 | I88: Y | J88: 0.472 | K88: -89.5 | L88: 6 | M88: 3 | N88: 2.77 | O88: 3 | P88: 2 | Q88: 13:40:59.9999999999976525 | R88: 6 | S88: 5.9 | T88: 18.43 | U88: 6.63 | V88: 6.63 | W88: 100 | Y88: 51 | Z88: 2.1 | AA88: 0 | AB88: 12:28:00.00000000000362550 | AC88: 33.6 | AD88: 10.8
A89: Cole Reinhardt | C89: 0 | D89: W | E89: 2500 | F89: VGK | G89: @ TOR | H89: 18:59:59.9999999999968050 | I89: Y | J89: 0.417 | K89: -71.5 | L89: 6.5 | M89: 3.25 | N89: 3.2 | O89: 4 | Q89: 09:39:00.00000000000127800 | R89: 2.3 | S89: 3.65 | T89: 9.86 | U89: 2.56 | V89: 2.56 | W89: 100 | Y89: 21 | Z89: 1 | AA89: 0
A90: Colin Blackwell | C90: 0 | D90: W | E90: 2500 | F90: DAL | G90: vs STL | H90: 20:00:00.0000000000031950 | I90: Y | J90: 0.486 | K90: -94.5 | L90: 5.5 | M90: 3.07 | N90: 2.75 | O90: 4 | Q90: 11:37:59.999999999999893725 | R90: 2.9 | S90: 3.68 | T90: 10.97 | U90: 3.61 | V90: 3.61 | W90: 100 | Y90: 37 | Z90: 1.4 | AA90: 0 | AB90: 10:37:59.99999999999829150 | AC90: 0
A91: Collin Graf | C91: 0 | D91: W | E91: 3500 | F91: SJ | G91: vs NYR | H91: 21:59:59.9999999999968050 | I91: Y | J91: 0.446 | K91: -80.5 | L91: 6.5 | M91: 3.38 | N91: 3.25 | O91: 1 | Q91: 16:26:00.00000000000085425 | R91: 6.6 | S91: 5.61 | T91: 21.68 | U91: 10.46 | V91: 10.46 | W91: 100 | Y91: 58 | Z91: 3 | AA91: 0 | AB91: 19:13:00.00000000000362550 | AC91: 10 | AD91: 2.9
A92: Colton Dach | C92: 0 | D92: C | E92: 2500 | F92: CHI | G92: vs TB | H92: 18:59:59.9999999999968050 | I92: N | J92: 0.386 | K92: 159 | L92: 6 | M92: 2.24 | N92: 3 | Q92: 11:56:00.00000000000085425 | R92: 3.3 | S92: 3.35 | T92: 0 | U92: 0 | V92: 0 | W92: 100 | Y92: 49 | Z92: 0 | AA92: 0
A93: Colton Parayko | C93: 0 | D93: D | E93: 3800 | F93: STL | G93: @ DAL | H93: 20:00:00.0000000000031950 | I93: N | J93: 0.514 | K93: 94.5 | L93: 5.5 | M93: 2.75 | N93: 3.07 | O93: 1 | Q93: 22:29:00.00000000000021525 | R93: 7.8 | S93: 4.42 | T93: 16.66 | U93: 7.82 | V93: 7.82 | W93: 100 | Y93: 72 | Z93: 2.1 | AA93: 0 | AB93: 21:52:59.99999999999829150 | AC93: 4.1 | AD93: 1.1
A94: Colton Sissons | C94: 0 | D94: C | E94: 2500 | F94: VGK | G94: @ TOR | H94: 18:59:59.9999999999968050 | I94: Y | J94: 0.417 | K94: -71.5 | L94: 6.5 | M94: 3.25 | N94: 3.2 | Q94: 11:46:59.99999999999797200 | R94: 3.4 | S94: 3.97 | T94: 0 | U94: 0 | V94: 0 | W94: 100 | Y94: 42 | Z94: 0 | AA94: 0
A95: Colton White | C95: 0 | D95: D | E95: 2500 | F95: NJ | G95: @ VAN | H95: 21:59:59.9999999999968050 | I95: Y | J95: 0.472 | K95: -89.5 | L95: 6 | M95: 3 | N95: 2.77 | Q95: 12:10:59.9999999999976525 | R95: 2.5 | S95: 2.23 | T95: 0 | U95: 0 | V95: 0 | W95: 100 | Y95: 55 | Z95: 0 | AA95: 0
A96: Connor Bedard | C96: 0 | D96: C | E96: 7800 | F96: CHI | G96: vs TB | H96: 18:59:59.9999999999968050 | I96: N | J96: 0.386 | K96: 159 | L96: 6 | M96: 2.24 | N96: 3 | O96: 1 | P96: 1 | Q96: 20:54:00.00000000000127800 | R96: 15.3 | S96: 11.02 | T96: 35.86 | U96: 13.82 | V96: 13.82 | W96: 100 | Y96: 64 | Z96: 1.8 | AA96: 0 | AB96: 21:36:00.00000000000191700 | AC96: 1.3 | AD96: 0.2
A97: Connor Brown | C97: 0 | D97: W | E97: 2800 | F97: NJ | G97: @ VAN | H97: 21:59:59.9999999999968050 | I97: Y | J97: 0.472 | K97: -89.5 | L97: 6 | M97: 3 | N97: 2.77 | O97: 4 | P97: 1 | Q97: 16:21:00.00000000000191700 | R97: 5.8 | S97: 5.91 | T97: 17.93 | U97: 6.11 | V97: 6.11 | W97: 100 | Y97: 49 | Z97: 2.2 | AA97: 0 | AB97: 18:37:00.00000000000170850 | AC97: 11.3 | AD97: 4
A98: Connor McMichael | C98: 0 | D98: W | E98: 4500 | F98: WSH | G98: @ CGY | H98: 21:00:00.000 | I98: Y | J98: 0.459 | K98: -85 | L98: 6 | M98: 3 | N98: 2.8 | O98: 1 | P98: 2 | Q98: 17:07:00.00000000000170850 | R98: 7.3 | S98: 6.97 | T98: 22.92 | U98: 8.98 | V98: 8.98 | W98: 100 | Y98: 52 | Z98: 2 | AA98: 0 | AB98: 12:30:00.0000000000031950 | AC98: 1.5 | AD98: 0.3
A99: Connor Murphy | C99: 0 | D99: D | E99: 2700 | F99: CHI | G99: vs TB | H99: 18:59:59.9999999999968050 | I99: N | J99: 0.386 | K99: 159 | L99: 6 | M99: 2.24 | N99: 3 | O99: 3 | Q99: 16:11:00.00000000000404925 | R99: 4.6 | S99: 4.8 | T99: 14.25 | U99: 4.65 | V99: 4.65 | W99: 100 | Y99: 48 | Z99: 1.7 | AA99: 0 | AB99: 17:33:59.99999999999595075 | AC99: 6.9 | AD99: 2.6
A100: Connor Zary | C100: 0 | D100: W | E100: 3400 | F100: CGY | G100: vs WSH | H100: 21:00:00.000 | I100: N | J100: 0.541 | K100: 85 | L100: 6 | M100: 2.8 | N100: 3 | O100: 1 | P100: 2 | Q100: 14:27:59.99999999999722875 | R100: 5.1 | S100: 5.36 | T100: 17.84 | U100: 7.12 | V100: 7.12 | W100: 100 | Y100: 47 | Z100: 2.1 | AA100: 0 | AB100: 14:23:59.99999999999808300 | AC100: 6.3 | AD100: 1.9
...
