Workbook

Sheet Actual
A1: Player | B1: Roster Position | C1: %Drafted | D1: FPTS
A2: Aaron Ekblad | B2: D | C2: 0.0101 | D2: 1.3
A3: Aatu Raty | B3: C | C3: 0.0017 | D3: 0
A4: Adam Gaudette | B4: W | C4: 0.0017 | D4: 10
A5: Adam Larsson | B5: D | C5: 0.0168 | D5: 6.5
A6: Adam Lowry | B6: C | C6: 0.0017 | D6: 5.8
A7: Adam Pelech | B7: D | C7: 0.0034 | D7: 9.5
A8: Adin Hill | B8: G | C8: 0.0017 | D8: 4.1
A9: Adrian Kempe | B9: UTIL | C9: 0.0067 | D9: 14.5
A10: Alex DeBrincat | B10: W | C10: 0.0859 | D10: 36.8
A11: Alex Iafallo | B11: UTIL | C11: 0.0017 | D11: 0
A12: Alex Killorn | B12: W | C12: 0.0623 | D12: 3
A13: Alex Laferriere | B13: C | C13: 0.0236 | D13: 7.3
... A457: Zack Bolduc | B457: W | C457: 0.0017 | D457: 17.1

Sheet Projection
A1: name | B1: team | C1: position | D1: salary | E1: projected_fpts | F1: dk_avg_fpts | G1: edge | H1: value | I1: floor | J1: ceiling | K1: predicted_ownership | L1: ownership_tier | M1: leverage_score | N1: dk_id | O1: actual | P1: own
A2: Juraj Slafkovsk√Ω | B2: MTL | C2: W | D2: 5200 | E2: 9.9480722 | F2: 9.86 | G2: 0.088072212 | H2: 1.9130908 | I2: 2.4870181 | J2: 29.870181 | K2: 0.8068629 | L2: Contrarian (<5%) | M2: 5.505715 | N2: 41766895 | O2: =IFERROR(VLOOKUP($A2,Actual!$A:$D,4,FALSE),IFERROR(VLOOKUP($A2,FC!$A:$AD,29,FALSE),"Not Found")) -> 22.1 | P2: =IFERROR(VLOOKUP($A2,Actual!$A:$D,3,FALSE),"0") -> 0.0152
A3: Mitch Marner | B3: VGK | C3: W | D3: 6300 | E3: 12.656876 | F3: 10.09 | G3: 2.5668763 | H3: 2.009028 | I3: 3.1642191 | J3: 36.642191 | K3: 3.9911772 | L3: Contrarian (<5%) | M3: 2.5358499 | N3: 41766469 | O3: =IFERROR(VLOOKUP($A3,Actual!$A:$D,4,FALSE),IFERROR(VLOOKUP($A3,FC!$A:$AD,29,FALSE),"Not Found")) -> 16.5 | P3: =IFERROR(VLOOKUP($A3,Actual!$A:$D,3,FALSE),"0") -> 0.0152
A4: Mike Matheson | B4: MTL | C4: D | D4: 4000 | E4: 8.1126446 | F4: 8.83 | G4: -0.71735536 | H4: 2.0281612 | I4: 2.0281612 | J4: 25.281612 | K4: 2.0759047 | L4: Contrarian (<5%) | M4: 2.6374824 | N4: 41767593 | O4: =IFERROR(VLOOKUP($A4,Actual!$A:$D,4,FALSE),IFERROR(VLOOKUP($A4,FC!$A:$AD,29,FALSE),"Not Found")) -> 11.3 | P4: =IFERROR(VLOOKUP($A4,Actual!$A:$D,3,FALSE),"0") -> 0.0101
A5: Alexander Wennberg | B5: SJS | C5: C | D5: 4300 | E5: 7.6295778 | F5: 8.1 | G5: -0.47042225 | H5: 1.7743204 | I5: 1.9073944 | J5: 24.073944 | K5: 3.0701363 | L5: Contrarian (<5%) | M5: 1.8745264 | N5: 41766535 | O5: =IFERROR(VLOOKUP($A5,Actual!$A:$D,4,FALSE),IFERROR(VLOOKUP($A5,FC!$A:$AD,29,FALSE),"Not Found")) -> 9.5 | P5: =IFERROR(VLOOKUP($A5,Actual!$A:$D,3,FALSE),"0") -> 0.0152
A6: Jake Middleton | B6: MIN | C6: D | D6: 2700 | E6: 5.2051574 | F6: 4.91 | G6: 0.2951574 | H6: 1.9278361 | I6: 1.3012893 | J6: 18.012893 | K6: 0.69196824 | L6: Contrarian (<5%) | M6: 3.0763919 | N6: 41767763 | O6: =IFERROR(VLOOKUP($A6,Actual!$A:$D,4,FALSE),IFERROR(VLOOKUP($A6,FC!$A:$AD,29,FALSE),"Not Found")) -> 7.8 | P6: =IFERROR(VLOOKUP($A6,Actual!$A:$D,3,FALSE),"0") -> 0.0084
A7: Joel Eriksson Ek | B7: MIN | C7: C | D7: 6000 | E7: 11.814814 | F7: 10.26 | G7: 1.5548137 | H7: 1.9691356 | I7: 2.9537034 | J7: 34.537034 | K7: 3.9911772 | L7: Contrarian (<5%) | M7: 2.3671397 | N7: 41766483 | O7: =IFERROR(VLOOKUP($A7,Actual!$A:$D,4,FALSE),IFERROR(VLOOKUP($A7,FC!$A:$AD,29,FALSE),"Not Found")) -> 5 | P7: =IFERROR(VLOOKUP($A7,Actual!$A:$D,3,FALSE),"0") -> 0.0606
A8: Matthew Knies | B8: TOR | C8: W | D8: 4700 | E8: 10.394466 | F8: 9.27 | G8: 1.1244661 | H8: 2.2115885 | I8: 2.5986165 | J8: 30.986165 | K8: 1.2102943 | L8: Contrarian (<5%) | M8: 4.702752 | N8: 41766927 | O8: =IFERROR(VLOOKUP($A8,Actual!$A:$D,4,FALSE),IFERROR(VLOOKUP($A8,FC!$A:$AD,29,FALSE),"Not Found")) -> 4.5 | P8: =IFERROR(VLOOKUP($A8,Actual!$A:$D,3,FALSE),"0") -> 0.0135
A9: Matt Coronato | B9: CGY | C9: W | D9: 4300 | E9: 10.384159 | F9: 8.05 | G9: 2.3341589 | H9: 2.4149207 | I9: 2.5960397 | J9: 30.960397 | K9: 1.9451159 | L9: Contrarian (<5%) | M9: 3.5258914 | N9: 41766949 | O9: =IFERROR(VLOOKUP($A9,Actual!$A:$D,4,FALSE),IFERROR(VLOOKUP($A9,FC!$A:$AD,29,FALSE),"Not Found")) -> 4.5 | P9: =IFERROR(VLOOKUP($A9,Actual!$A:$D,3,FALSE),"0") -> 0.0152
A10: Alexis Lafreni√®re | B10: NYR | C10: W | D10: 4000 | E10: 8.4315309 | F10: 7.24 | G10: 1.1915309 | H10: 2.1078827 | I10: 2.1078827 | J10: 26.078827 | K10: 0.79799627 | L10: Contrarian (<5%) | M10: 4.689404 | N10: 41766973 | O10: =IFERROR(VLOOKUP($A10,Actual!$A:$D,4,FALSE),IFERROR(VLOOKUP($A10,FC!$A:$AD,29,FALSE),"Not Found")) -> 2.8 | P10: =IFERROR(VLOOKUP($A10,Actual!$A:$D,3,FALSE),"0") -> 0.0101
A11: Charlie Lindgren | B11: WSH | C11: G | D11: 7500 | E11: 9.2877878 | F11: 10.27 | G11: -0.98221216 | H11: 1.2383717 | I11: 1.8575576 | J11: 28.575576 | K11: 4.9591414 | L11: Contrarian (<5%) | M11: 1.5585782 | N11: 41768112 | O11: =IFERROR(VLOOKUP($A11,Actual!$A:$D,4,FALSE),IFERROR(VLOOKUP($A11,FC!$A:$AD,29,FALSE),"Not Found")) -> 8.1 | P11: =IFERROR(VLOOKUP($A11,Actual!$A:$D,3,FALSE),"0") -> 0.0084
A12: Jake Oettinger | B12: DAL | C12: G | D12: 7400 | E12: 12.814866 | F12: 11.96 | G12: 0.85486631 | H12: 1.7317387 | I12: 2.5629733 | J12: 35.629733 | K12: 4.1961966 | L12: Contrarian (<5%) | M12: 2.4662012 | N12: 41768117 | O12: =IFERROR(VLOOKUP($A12,Actual!$A:$D,4,FALSE),IFERROR(VLOOKUP($A12,FC!$A:$AD,29,FALSE),"Not Found")) -> 3.9 | P12: =IFERROR(VLOOKUP($A12,Actual!$A:$D,3,FALSE),"0") -> 0.0286
A13: Adin Hill | B13: VGK | C13: G | D13: 8000 | E13: 4.9045827 | F13: 4.39 | G13: 0.51458269 | H13: 0.61307284 | I13: 0.98091654 | J13: 19.809165 | K13: 2.9754849 | L13: Contrarian (<5%) | M13: 1.2337068 | N13: 41768088 | O13: =IFERROR(VLOOKUP($A13,Actual!$A:$D,4,FALSE),IFERROR(VLOOKUP($A13,FC!$A:$AD,29,FALSE),"Not Found")) -> 4.1 | P13: =IFERROR(VLOOKUP($A13,Actual!$A:$D,3,FALSE),"0") -> 0.0017
... A645: Lane Pederson | B645: PHI | C645: C | D645: 2500 | E645: 0.86931543 | F645: 0.78 | G645: 0.089315435 | H645: 0.34772617 | I645: 0.21732886 | J645: 7.1732886 | K645: 0.40935151 | L645: Contrarian (<5%) | M645: 0.61681946 | N645: 41766691 | O645: =IFERROR(VLOOKUP($A645,Actual!$A:$D,4,FALSE),IFERROR(VLOOKUP($A645,FC!$A:$AD,29,FALSE),"Not Found")) -> 0 | P645: =IFERROR(VLOOKUP($A645,Actual!$A:$D,3,FALSE),"0") -> 0

Sheet NHT

Sheet FC
A1: Player | B1: Inj | C1: Likes | D1: Pos | E1: Salary | F1: Team | G1: Opp | H1: Time | I1: Fav. | J1: Win % | K1: Spread | L1: Total | M1: TeamGoal | N1: OppGoal | O1: Start/Line | P1: PP Unit | Q1: avg TOI | R1: Avg | S1: STDV | T1: Ceiling | U1: FC Proj | V1: My Proj | W1: Exp. | X1: Used | Y1: Con. | Z1: Value | AA1: Own% | AB1: TOI | AC1: Score | AD1: Val
A2: A.j. Greer | C2: 0 | D2: W | E2: 2500 | F2: FLA | G2: @ STL | H2: 0.83333333 | I2: Y | J2: 0.487 | K2: -95 | L2: 5.5 | M2: 2.75 | N2: 2.54 | O2: 4 | Q2: 0.47638889 | R2: 4.9 | S2: 5.84 | T2: 16.88 | U2: 5.2 | V2: 5.2 | W2: 100 | Y2: 40 | Z2: 2.1 | AA2: 0 | AB2: 0.31041667 | AC2: 11.5 | AD2: 4.6
A3: Aaron Ekblad | C3: 0 | D3: D | E3: 3900 | F3: FLA | G3: @ STL | H3: 0.83333333 | I3: Y | J3: 0.487 | K3: -95 | L3: 5.5 | M3: 2.75 | N3: 2.54 | O3: 1 | Q3: 0.92777778 | R3: 7.3 | S3: 5.29 | T3: 18.84 | U3: 8.26 | V3: 8.26 | W3: 100 | Y3: 64 | Z3: 2.1 | AA3: 0 | AB3: 0.96527778 | AC3: 1.3 | AD3: 0.3
A4: Aatu Raty | C4: 0 | D4: C | E4: 2600 | F4: VAN | G4: vs ANA | H4: 0.91666667 | I4: N | J4: 0.512 | K4: 95.5 | L4: 6.5 | M4: 3.01 | N4: 3.25 | O4: 3 | Q4: 0.50625 | R4: 3.8 | S4: 5.11 | T4: 14.45 | U4: 4.23 | V4: 4.23 | W4: 100 | Y4: 33 | Z4: 1.6 | AA4: 0 | AB4: 0.5375 | AC4: 0
A5: Adam Boqvist | C5: 0 | D5: D | E5: 2500 | F5: NYI | G5: @ NYR | H5: 0.79166667 | I5: Y | J5: 0.472 | K5: -89.5 | L5: 6 | M5: 3 | N5: 2.82 | Q5: 0.53472222 | R5: 2.3 | S5: 2.77 | T5: 0 | U5: 0 | V5: 0 | W5: 100 | Y5: 40 | Z5: 0 | AA5: 0
A6: Adam Edstrom | C6: 0 | D6: C | E6: 2500 | F6: NYR | G6: vs NYI | H6: 0.79166667 | I6: N | J6: 0.528 | K6: 89.5 | L6: 6 | M6: 2.82 | N6: 3 | Q6: 0.40347222 | R6: 3.6 | S6: 3.99 | T6: 0 | U6: 0 | V6: 0 | W6: 100 | Y6: 45 | Z6: 0 | AA6: 0
A7: Adam Engstrom | C7: 0 | D7: D | E7: 2500 | F7: MTL | G7: vs COL | H7: 0.79166667 | I7: N | J7: 0.551 | K7: 81.5 | L7: 6.5 | M7: 3.17 | N7: 3.25 | Q7: 0.54097222 | R7: 1.9 | S7: 1.96 | T7: 0 | U7: 0 | V7: 0 | W7: 100 | Y7: 48 | Z7: 0 | AA7: 0
A8: Adam Erne | C8: 0 | D8: W | E8: 2500 | F8: DAL | G8: @ VGK | H8: 0.91666667 | I8: N | J8: 0.535 | K8: 87 | L8: 6 | M8: 3 | N8: 3.14 | O8: 4 | Q8: 0.39305556 | R8: 3.8 | S8: 4.24 | T8: 12.98 | U8: 4.5 | V8: 4.5 | W8: 100 | Y8: 44 | Z8: 1.8 | AA8: 0 | AB8: 0.44652778 | AC8: 0
A9: Adam Fox | C9: 0 | D9: D | E9: 6400 | F9: NYR | G9: vs NYI | H9: 0.79166667 | I9: N | J9: 0.528 | K9: 89.5 | L9: 6 | M9: 2.82 | N9: 3 | Q9: 0.97708333 | R9: 11 | S9: 6.33 | T9: 0 | U9: 0 | V9: 0 | W9: 100 | Y9: 71 | Z9: 0 | AA9: 0
A10: Adam Gaudette | C10: 0 | D10: W | E10: 2900 | F10: SJ | G10: @ EDM | H10: 0.875 | I10: N | J10: 0.471 | K10: 112.5 | L10: 7 | M10: 3.5 | N10: 4.05 | O10: 3 | Q10: 0.49930556 | R10: 6.2 | S10: 5.9 | T10: 20.39 | U10: 8.59 | V10: 8.59 | W10: 100 | Y10: 52 | Z10: 3 | AA10: 0 | AB10: 0.51388889 | AC10: 10 | AD10: 3.4
A11: Adam Ginning | C11: 0 | D11: D | E11: 2500 | F11: PHI | G11: @ BOS | H11: 0.79166667 | I11: N | J11: 0.519 | K11: 92.5 | L11: 6.5 | M11: 3.25 | N11: 3.62 | Q11: 0.64097222 | R11: 2.6 | S11: 1.67 | T11: 0 | U11: 0 | V11: 0 | W11: 100 | Y11: 68 | Z11: 0 | AA11: 0
A12: Adam Henrique | C12: 0 | D12: C | E12: 2800 | F12: EDM | G12: vs SJ | H12: 0.875 | I12: Y | J12: 0.529 | K12: -112.5 | L12: 7 | M12: 4.05 | N12: 3.5 | Q12: 0.57708333 | R12: 5.8 | S12: 5.33 | T12: 0 | U12: 0 | V12: 0 | W12: 100 | Y12: 54 | Z12: 0 | AA12: 0
A13: Adam Klapka | C13: 0 | D13: W | E13: 2700 | F13: CGY | G13: @ MIN | H13: 0.83333333 | I13: N | J13: 0.487 | K13: 105.5 | L13: 6 | M13: 3 | N13: 3.46 | O13: 4 | Q13: 0.44166667 | R13: 4 | S13: 4.15 | T13: 12.45 | U13: 4.15 | V13: 4.15 | W13: 100 | Y13: 48 | Z13: 1.5 | AA13: 0 | AB13: 0.38680556 | AC13: 1.5 | AD13: 0.6
A14: Adam Larsson | C14: 0 | D14: D | E14: 3200 | F14: SEA | G14: vs TOR | H14: 0.91666667 | I14: Y | J14: 0.415 | K14: -71 | L14: 6 | M14: 3.02 | N14: 3 | O14: 1 | Q14: 0.90486111 | R14: 7 | S14: 4.9 | T14: 18.12 | U14: 8.32 | V14: 8.32 | W14: 100 | Y14: 65 | Z14: 2.6 | AA14: 0 | AB14: 0.77291667 | AC14: 6.5 | AD14: 2
A15: Adam Lowry | C15: 0 | D15: C | E15: 2500 | F15: WPG | G15: @ TB | H15: 0.79166667 | I15: N | J15: 0.482 | K15: 107.5 | L15: 5.5 | M15: 2.75 | N15: 3.2 | O15: 3 | Q15: 0.60069444 | R15: 4.4 | S15: 4.43 | T15: 12.86 | U15: 4 | V15: 4 | W15: 100 | Y15: 50 | Z15: 1.6 | AA15: 0 | AB15: 0.60069444 | AC15: 5.8 | AD15: 2.3
A16: Adam Pelech | C16: 0 | D16: D | E16: 3300 | F16: NYI | G16: @ NYR | H16: 0.79166667 | I16: Y | J16: 0.472 | K16: -89.5 | L16: 6 | M16: 3 | N16: 2.82 | O16: 2 | Q16: 0.86319444 | R16: 6.5 | S16: 3.92 | T16: 15.99 | U16: 8.15 | V16: 8.15 | W16: 100 | Y16: 70 | Z16: 2.5 | AA16: 0 | AB16: 0.88819444 | AC16: 9.5 | AD16: 2.9
A17: Adam Wilsby | C17: 0 | D17: D | E17: 2500 | F17: NSH | G17: @ NJ | H17: 0.79166667 | I17: N | J17: 0.536 | K17: 86.5 | L17: 6 | M17: 3 | N17: 3.19 | O17: 2 | Q17: 0.71041667 | R17: 3.8 | S17: 3.66 | T17: 11.9 | U17: 4.58 | V17: 4.58 | W17: 100 | Y17: 52 | Z17: 1.8 | AA17: 0 | AB17: 0.66875 | AC17: 9.3 | AD17: 3.7
A18: Adin Hill | C18: 0 | D18: G | E18: 8000 | F18: VGK | G18: vs DAL | H18: 0.91666667 | I18: Y | J18: 0.465 | K18: -87 | L18: 6 | M18: 3.14 | N18: 3 | O18: confirm | Q18: 2.1590278 | R18: 4.4 | S18: 7.27 | T18: 22.05 | U18: 7.51 | V18: 7.51 | W18: 100 | Y18: 17 | Z18: 0.9 | AA18: 0 | AB18: 2.6701389 | AC18: 4.1 | AD18: 0.5
A19: Adrian Kempe | C19: 0 | D19: W | E19: 6000 | F19: LA | G19: @ BUF | H19: 0.79166667 | I19: N | J19: 0.565 | K19: 77 | L19: 5.5 | M19: 2.75 | N19: 2.87 | O19: 1 | P19: 1 | Q19: 0.8 | R19: 10.3 | S19: 6.35 | T19: 22.18 | U19: 9.48 | V19: 9.48 | W19: 100 | Y19: 69 | Z19: 1.6 | AA19: 0 | AB19: 0.70069444 | AC19: 14.5 | AD19: 2.4
A20: Akira Schmid | C20: 0 | D20: G | E20: 8000 | F20: VGK | G20: vs DAL | H20: 0.91666667 | I20: Y | J20: 0.465 | K20: -87 | L20: 6 | M20: 3.14 | N20: 3 | O20: unlikely | Q20: 2.4208333 | R20: 10.7 | S20: 8.21 | T20: 0 | U20: 0 | V20: 0 | W20: 100 | Y20: 62 | Z20: 0 | AA20: 0 | AB20: 0 | AC20: 2 | AD20: 0.3
A21: Albert Johansson | C21: 0 | D21: D | E21: 2500 | F21: DET | G21: vs WSH | H21: 0.8125 | I21: Y | J21: 0.44 | K21: -78.5 | L21: 6.5 | M21: 3.43 | N21: 3.25 | O21: 3 | Q21: 0.66180556 | R21: 4.3 | S21: 4.02 | T21: 13.56 | U21: 5.52 | V21: 5.52 | W21: 100 | Y21: 53 | Z21: 2.2 | AA21: 0 | AB21: 0.80277778 | AC21: 2.6 | AD21: 1
A22: Alec Regula | C22: 0 | D22: D | E22: 2500 | F22: EDM | G22: vs SJ | H22: 0.875 | I22: Y | J22: 0.529 | K22: -112.5 | L22: 7 | M22: 4.05 | N22: 3.5 | Q22: 0.60902778 | R22: 4.2 | S22: 3.52 | T22: 0 | U22: 0 | V22: 0 | W22: 100 | Y22: 58 | Z22: 0 | AA22: 0
A23: Aleksander Barkov | B23: ! | C23: 0 | D23: C | E23: 2500 | F23: FLA | G23: @ STL | H23: 0.83333333 | I23: Y | J23: 0.487 | K23: -95 | L23: 5.5 | M23: 2.75 | N23: 2.54 | T23: 0 | U23: 0 | V23: 0 | W23: 100 | Y23: 0 | Z23: 0 | AA23: 0
A24: Aleksanteri Kaskimaki | C24: 0 | D24: C | E24: 2500 | F24: STL | G24: vs FLA | H24: 0.83333333 | I24: N | J24: 0.513 | K24: 95 | L24: 5.5 | M24: 2.54 | N24: 2.75 | Q24: 0.47083333 | R24: 3.8 | S24: 3.48 | T24: 0 | U24: 0 | V24: 0 | W24: 100 | Y24: 54 | Z24: 0 | AA24: 0
A25: Alex DeBrincat | C25: 0 | D25: W | E25: 6600 | F25: DET | G25: vs WSH | H25: 0.8125 | I25: Y | J25: 0.44 | K25: -78.5 | L25: 6.5 | M25: 3.43 | N25: 3.25 | O25: 2 | P25: 1 | Q25: 0.75555556 | R25: 14.2 | S25: 9.17 | T25: 35.82 | U25: 17.48 | V25: 17.48 | W25: 100 | Y25: 68 | Z25: 2.6 | AA25: 0 | AB25: 0.89444444 | AC25: 36.8 | AD25: 5.6
A26: Alex Iafallo | C26: 0 | D26: W | E26: 3000 | F26: WPG | G26: @ TB | H26: 0.79166667 | I26: N | J26: 0.482 | K26: 107.5 | L26: 5.5 | M26: 2.75 | N26: 3.2 | O26: 2 | P26: 2 | Q26: 0.6375 | R26: 5.7 | S26: 5.27 | T26: 15.93 | U26: 5.39 | V26: 5.39 | W26: 100 | Y26: 54 | Z26: 1.8 | AA26: 0 | AB26: 0.66319444 | AC26: 0
A27: Alex Killorn | C27: 0 | D27: W | E27: 3700 | F27: ANA | G27: @ VAN | H27: 0.91666667 | I27: Y | J27: 0.488 | K27: -95.5 | L27: 6.5 | M27: 3.25 | N27: 3.01 | O27: 1 | P27: 2 | Q27: 0.66527778 | R27: 5.5 | S27: 4.79 | T27: 16.73 | U27: 7.15 | V27: 7.15 | W27: 100 | Y27: 56 | Z27: 1.9 | AA27: 0 | AB27: 0.81736111 | AC27: 3 | AD27: 0.8
A28: Alex Laferriere | C28: 0 | D28: C | E28: 4700 | F28: LA | G28: @ BUF | H28: 0.79166667 | I28: N | J28: 0.565 | K28: 77 | L28: 5.5 | M28: 2.75 | N28: 2.87 | O28: 1 | P28: 2 | Q28: 0.72083333 | R28: 8.2 | S28: 7.31 | T28: 23.4 | U28: 8.78 | V28: 8.78 | W28: 100 | Y28: 55 | Z28: 1.9 | AA28: 0 | AB28: 0.73611111 | AC28: 7.3 | AD28: 1.6
A29: Alex Lyon | C29: 0 | D29: G | E29: 8000 | F29: BUF | G29: vs LA | H29: 0.79166667 | I29: Y | J29: 0.435 | K29: -77 | L29: 5.5 | M29: 2.87 | N29: 2.75 | O29: confirm | Q29: 2.26875 | R29: 12.5 | S29: 8.91 | T29: 29.32 | U29: 11.5 | V29: 11.5 | W29: 100 | Y29: 64 | Z29: 1.4 | AA29: 0 | AB29: 2.5 | AC29: 31.4 | AD29: 3.9
A30: Alex Nedeljkovic | C30: 0 | D30: G | E30: 7000 | F30: SJ | G30: @ EDM | H30: 0.875 | I30: N | J30: 0.471 | K30: 112.5 | L30: 7 | M30: 3.5 | N30: 4.05 | O30: unlikely | Q30: 2.3888889 | R30: 11 | S30: 9.84 | T30: 0 | U30: 0 | V30: 0 | W30: 100 | Y30: 55 | Z30: 0 | AA30: 0 | AB30: 0 | AC30: 2 | AD30: 0.3
A31: Alex Newhook | C31: 0 | D31: W | E31: 2500 | F31: MTL | G31: vs COL | H31: 0.79166667 | I31: N | J31: 0.551 | K31: 81.5 | L31: 6.5 | M31: 3.17 | N31: 3.25 | Q31: 0.60625 | R31: 7.4 | S31: 7.17 | T31: 0 | U31: 0 | V31: 0 | W31: 100 | Y31: 52 | Z31: 0 | AA31: 0
A32: Alex Ovechkin | C32: 0 | D32: W | E32: 6800 | F32: WSH | G32: @ DET | H32: 0.8125 | I32: N | J32: 0.56 | K32: 78.5 | L32: 6.5 | M32: 3.25 | N32: 3.43 | O32: 3 | P32: 2 | Q32: 0.74861111 | R32: 10.2 | S32: 7.44 | T32: 27.63 | U32: 12.75 | V32: 12.75 | W32: 100 | Y32: 64 | Z32: 1.9 | AA32: 0 | AB32: 0.66666667 | AC32: 11 | AD32: 1.6
A33: Alexander Petrovic | C33: 0 | D33: D | E33: 2500 | F33: DAL | G33: @ VGK | H33: 0.91666667 | I33: N | J33: 0.535 | K33: 87 | L33: 6 | M33: 3 | N33: 3.14 | O33: 3 | Q33: 0.65625 | R33: 5.2 | S33: 4.57 | T33: 14.72 | U33: 5.58 | V33: 5.58 | W33: 100 | Y33: 56 | Z33: 2.2 | AA33: 0 | AB33: 0.55902778 | AC33: 6.9 | AD33: 2.8
A34: Alex Pietrangelo | B34: ! | C34: 0 | D34: D | E34: 2700 | F34: VGK | G34: vs DAL | H34: 0.91666667 | I34: Y | J34: 0.465 | K34: -87 | L34: 6 | M34: 3.14 | N34: 3 | T34: 0 | U34: 0 | V34: 0 | W34: 100 | Y34: 0 | Z34: 0 | AA34: 0
A35: Alex Steeves | C35: 0 | D35: W | E35: 2700 | F35: BOS | G35: vs PHI | H35: 0.79166667 | I35: Y | J35: 0.481 | K35: -92.5 | L35: 6.5 | M35: 3.62 | N35: 3.25 | Q35: 0.51111111 | R35: 5.5 | S35: 5.87 | T35: 0 | U35: 0 | V35: 0 | W35: 100 | Y35: 47 | Z35: 0 | AA35: 0
A36: Alex Tuch | C36: 0 | D36: W | E36: 6100 | F36: BUF | G36: vs LA | H36: 0.79166667 | I36: Y | J36: 0.435 | K36: -77 | L36: 5.5 | M36: 2.87 | N36: 2.75 | O36: 1 | P36: 2 | Q36: 0.77638889 | R36: 11.1 | S36: 6.19 | T36: 24.34 | U36: 11.96 | V36: 11.96 | W36: 100 | Y36: 72 | Z36: 2 | AA36: 0 | AB36: 0.74791667 | AC36: 45 | AD36: 7.4
A37: Alex Turcotte | C37: 0 | D37: C | E37: 3100 | F37: LA | G37: @ BUF | H37: 0.79166667 | I37: N | J37: 0.565 | K37: 77 | L37: 5.5 | M37: 2.75 | N37: 2.87 | Q37: 0.45486111 | R37: 4 | S37: 4.65 | T37: 0 | U37: 0 | V37: 0 | W37: 100 | Y37: 42 | Z37: 0 | AA37: 0
A38: Alex Vlasic | C38: 0 | D38: D | E38: 2600 | F38: CHI | G38: @ PIT | H38: 0.79166667 | I38: N | J38: 0.493 | K38: 103 | L38: 6.5 | M38: 3.25 | N38: 3.71 | O38: 1 | Q38: 0.87291667 | R38: 5.4 | S38: 4.19 | T38: 14.56 | U38: 6.18 | V38: 6.18 | W38: 100 | Y38: 61 | Z38: 2.4 | AA38: 0 | AB38: 0.82777778 | AC38: 2.6 | AD38: 1
A39: Alex Wennberg | C39: 0 | D39: C | E39: 4300 | F39: SJ | G39: @ EDM | H39: 0.875 | I39: N | J39: 0.471 | K39: 112.5 | L39: 7 | M39: 3.5 | N39: 4.05 | O39: 2 | P39: 1 | Q39: 0.86180556 | R39: 8.1 | S39: 6.97 | T39: 25.65 | U39: 11.71 | V39: 11.71 | W39: 100 | Y39: 57 | Z39: 2.7 | AA39: 0 | AB39: 0.88194444 | AC39: 9.5 | AD39: 2.2
A40: Alexander Holtz | C40: 0 | D40: W | E40: 2500 | F40: VGK | G40: vs DAL | H40: 0.91666667 | I40: Y | J40: 0.465 | K40: -87 | L40: 6 | M40: 3.14 | N40: 3 | O40: 4 | Q40: 0.48055556 | R40: 4.3 | S40: 5.13 | T40: 15.29 | U40: 5.03 | V40: 5.03 | W40: 100 | Y40: 40 | Z40: 2 | AA40: 0 | AB40: 0.54930556 | AC40: 0
A41: Alexander Kerfoot | C41: 0 | D41: W | E41: 2500 | F41: UTA | G41: @ CAR | H41: 0.79166667 | I41: N | J41: 0.494 | K41: 102.5 | L41: 6 | M41: 3 | N41: 3.44 | Q41: 0.43055556 | R41: 4.6 | S41: 4.98 | T41: 0 | U41: 0 | V41: 0 | W41: 100 | Y41: 46 | Z41: 0 | AA41: 0
A42: Alexander Nikishin | C42: 0 | D42: D | E42: 3500 | F42: CAR | G42: vs UTA | H42: 0.79166667 | I42: Y | J42: 0.506 | K42: -102.5 | L42: 6 | M42: 3.44 | N42: 3 | O42: 3 | P42: 2 | Q42: 0.78194444 | R42: 6.7 | S42: 4.88 | T42: 18.07 | U42: 8.31 | V42: 8.31 | W42: 100 | Y42: 64 | Z42: 2.4 | AA42: 0 | AB42: 0.68541667 | AC42: 3 | AD42: 0.9
A43: Alexander Romanov | C43: 0 | D43: D | E43: 2500 | F43: NYI | G43: @ NYR | H43: 0.79166667 | I43: Y | J43: 0.472 | K43: -89.5 | L43: 6 | M43: 3 | N43: 2.82 | Q43: 0.80694444 | R43: 5.7 | S43: 3.68 | T43: 0 | U43: 0 | V43: 0 | W43: 100 | Y43: 68 | Z43: 0 | AA43: 0
A44: Alexandre Carrier | C44: 0 | D44: D | E44: 3000 | F44: MTL | G44: vs COL | H44: 0.79166667 | I44: N | J44: 0.551 | K44: 81.5 | L44: 6.5 | M44: 3.17 | N44: 3.25 | O44: 2 | Q44: 0.81527778 | R44: 7.3 | S44: 5.61 | T44: 19.57 | U44: 8.35 | V44: 8.35 | W44: 100 | Y44: 62 | Z44: 2.8 | AA44: 0 | AB44: 0.80972222 | AC44: 14.1 | AD44: 4.7
A45: Alexandre Texier | C45: 0 | D45: W | E45: 4000 | F45: MTL | G45: vs COL | H45: 0.79166667 | I45: N | J45: 0.551 | K45: 81.5 | L45: 6.5 | M45: 3.17 | N45: 3.25 | O45: 1 | P45: 2 | Q45: 0.57569444 | R45: 6.1 | S45: 8.43 | T45: 25.32 | U45: 8.46 | V45: 8.46 | W45: 100 | Y45: 31 | Z45: 2.1 | AA45: 0 | AB45: 0.60625 | AC45: 2.8 | AD45: 0.7
A46: Alexei Kolosov | C46: 0 | D46: G | E46: 7100 | F46: PHI | G46: @ BOS | H46: 0.79166667 | I46: N | J46: 0.519 | K46: 92.5 | L46: 6.5 | M46: 3.25 | N46: 3.62 | O46: unlikely | Q46: 1.25 | R46: 0.8 | S46: 7.56 | T46: 0 | U46: 0 | V46: 0 | W46: 100 | Y46: 0 | Z46: 0 | AA46: 0
A47: Alexey Toropchenko | C47: 0 | D47: W | E47: 2500 | F47: STL | G47: vs FLA | H47: 0.83333333 | I47: N | J47: 0.513 | K47: 95 | L47: 5.5 | M47: 2.54 | N47: 2.75 | O47: 4 | Q47: 0.50833333 | R47: 4.2 | S47: 3.96 | T47: 11.91 | U47: 3.99 | V47: 3.99 | W47: 100 | Y47: 53 | Z47: 1.6 | AA47: 0 | AB47: 0.49444444 | AC47: 2.8 | AD47: 1.1
A48: Alexis Lafreniere | C48: 0 | D48: W | E48: 4000 | F48: NYR | G48: vs NYI | H48: 0.79166667 | I48: N | J48: 0.528 | K48: 89.5 | L48: 6 | M48: 2.82 | N48: 3 | O48: 2 | P48: 1 | Q48: 0.7125 | R48: 7.1 | S48: 6.35 | T48: 19.96 | U48: 7.26 | V48: 7.26 | W48: 100 | Y48: 55 | Z48: 1.8 | AA48: 0 | AB48: 0.74583333 | AC48: 2.8 | AD48: 0.7
A49: Aliaksei Protas | C49: 0 | D49: W | E49: 5100 | F49: WSH | G49: @ DET | H49: 0.8125 | I49: N | J49: 0.56 | K49: 78.5 | L49: 6.5 | M49: 3.25 | N49: 3.43 | O49: 2 | Q49: 0.7625 | R49: 9 | S49: 7.24 | T49: 25.69 | U49: 11.21 | V49: 11.21 | W49: 100 | Y49: 60 | Z49: 2.2 | AA49: 0 | AB49: 0.88125 | AC49: 4.3 | AD49: 0.8
A50: Anders Lee | C50: 0 | D50: W | E50: 5000 | F50: NYI | G50: @ NYR | H50: 0.79166667 | I50: Y | J50: 0.472 | K50: -89.5 | L50: 6 | M50: 3 | N50: 2.82 | O50: 3 | P50: 2 | Q50: 0.64861111 | R50: 8.7 | S50: 7.63 | T50: 25.14 | U50: 9.88 | V50: 9.88 | W50: 100 | Y50: 56 | Z50: 2 | AA50: 0 | AB50: 0.63055556 | AC50: 0
A51: Andre Burakovsky | C51: 0 | D51: W | E51: 3300 | F51: CHI | G51: @ PIT | H51: 0.79166667 | I51: N | J51: 0.493 | K51: 103 | L51: 6.5 | M51: 3.25 | N51: 3.71 | O51: 3 | P51: 2 | Q51: 0.72708333 | R51: 6.8 | S51: 6.31 | T51: 19.49 | U51: 6.87 | V51: 6.87 | W51: 100 | Y51: 54 | Z51: 2.1 | AA51: 0 | AB51: 0.46944444 | AC51: 0
A52: Andre Lee | C52: 0 | D52: W | E52: 2500 | F52: LA | G52: @ BUF | H52: 0.79166667 | I52: N | J52: 0.565 | K52: 77 | L52: 5.5 | M52: 2.75 | N52: 2.87 | Q52: 0.42777778 | R52: 3.6 | S52: 3.24 | T52: 0 | U52: 0 | V52: 0 | W52: 100 | Y52: 55 | Z52: 0 | AA52: 0
A53: Andreas Englund | C53: 0 | D53: D | E53: 2500 | F53: NSH | G53: @ NJ | H53: 0.79166667 | I53: N | J53: 0.536 | K53: 86.5 | L53: 6 | M53: 3 | N53: 3.19 | Q53: 0.32152778 | R53: 0 | S53: 0 | T53: 0 | U53: 0 | V53: 0 | W53: 100 | Y53: 0 | Z53: 0 | AA53: 0
A54: Andrei Kuzmenko | C54: 0 | D54: W | E54: 3400 | F54: LA | G54: @ BUF | H54: 0.79166667 | I54: N | J54: 0.565 | K54: 77 | L54: 5.5 | M54: 2.75 | N54: 2.87 | O54: 3 | P54: 1 | Q54: 0.63263889 | R54: 5.5 | S54: 4.89 | T54: 15.41 | U54: 5.63 | V54: 5.63 | W54: 100 | Y54: 56 | Z54: 1.7 | AA54: 0 | AB54: 0.65208333 | AC54: 2.8 | AD54: 0.8
A55: Andrei Svechnikov | C55: 0 | D55: W | E55: 6400 | F55: CAR | G55: vs UTA | H55: 0.79166667 | I55: Y | J55: 0.506 | K55: -102.5 | L55: 6 | M55: 3.44 | N55: 3 | O55: 1 | P55: 1 | Q55: 0.70416667 | R55: 10.3 | S55: 8.61 | T55: 31.86 | U55: 14.64 | V55: 14.64 | W55: 100 | Y55: 58 | Z55: 2.3 | AA55: 0 | AB55: 0.83263889 | AC55: 31 | AD55: 4.8
A56: Andrei Vasilevskiy | C56: 0 | D56: G | E56: 8500 | F56: TB | G56: vs WPG | H56: 0.79166667 | I56: Y | J56: 0.518 | K56: -107.5 | L56: 5.5 | M56: 3.2 | N56: 2.75 | O56: confirm | Q56: 2.4638889 | R56: 13.1 | S56: 8.73 | T56: 31.19 | U56: 13.73 | V56: 13.73 | W56: 100 | Y56: 67 | Z56: 1.6 | AA56: 0 | AB56: 2.4770833 | AC56: 17.9 | AD56: 2.1
A57: Andrew Agozzino | C57: 0 | D57: C | E57: 2500 | F57: UTA | G57: @ CAR | H57: 0.79166667 | I57: N | J57: 0.494 | K57: 102.5 | L57: 6 | M57: 3 | N57: 3.44 | Q57: 0.43888889 | R57: 3.9 | S57: 4.5 | T57: 0 | U57: 0 | V57: 0 | W57: 100 | Y57: 42 | Z57: 0 | AA57: 0
A58: Andrew Copp | C58: 0 | D58: C | E58: 3700 | F58: DET | G58: vs WSH | H58: 0.8125 | I58: Y | J58: 0.44 | K58: -78.5 | L58: 6.5 | M58: 3.43 | N58: 3.25 | O58: 2 | P58: 2 | Q58: 0.66527778 | R58: 6.8 | S58: 5.13 | T58: 21.34 | U58: 11.08 | V58: 11.08 | W58: 100 | Y58: 62 | Z58: 3 | AA58: 0 | AB58: 0.76180556 | AC58: 5 | AD58: 1.4
A59: Andrew Mangiapane | C59: 0 | D59: W | E59: 2500 | F59: EDM | G59: vs SJ | H59: 0.875 | I59: Y | J59: 0.529 | K59: -112.5 | L59: 7 | M59: 4.05 | N59: 3.5 | Q59: 0.53888889 | R59: 3.7 | S59: 3.79 | T59: 0 | U59: 0 | V59: 0 | W59: 100 | Y59: 49 | Z59: 0 | AA59: 0
A60: Andrew Peeke | C60: 0 | D60: D | E60: 2500 | F60: BOS | G60: vs PHI | H60: 0.79166667 | I60: Y | J60: 0.481 | K60: -92.5 | L60: 6.5 | M60: 3.62 | N60: 3.25 | O60: 3 | Q60: 0.82291667 | R60: 5.8 | S60: 4.63 | T60: 16.58 | U60: 7.32 | V60: 7.32 | W60: 100 | Y60: 60 | Z60: 2.9 | AA60: 0 | AB60: 0.83541667 | AC60: 11.5 | AD60: 4.6
A61: Angus Crookshank | C61: 0 | D61: W | E61: 2500 | F61: NJ | G61: vs NSH | H61: 0.79166667 | I61: Y | J61: 0.464 | K61: -86.5 | L61: 6 | M61: 3.19 | N61: 3 | Q61: 0.35763889 | R61: 3 | S61: 3.94 | T61: 0 | U61: 0 | V61: 0 | W61: 100 | Y61: 34 | Z61: 0 | AA61: 0
A62: Anson Thornton | C62: 0 | D62: G | E62: 7000 | F62: UTA | G62: @ CAR | H62: 0.79166667 | I62: N | J62: 0.494 | K62: 102.5 | L62: 6 | M62: 3 | N62: 3.44 | T62: 10.61 | U62: 10.61 | V62: 10.61 | W62: 100 | Y62: 0 | Z62: 1.5 | AA62: 0
A63: Anthony Beauvillier | C63: 0 | D63: W | E63: 3100 | F63: WSH | G63: @ DET | H63: 0.8125 | I63: N | J63: 0.56 | K63: 78.5 | L63: 6.5 | M63: 3.25 | N63: 3.43 | O63: 4 | Q63: 0.65347222 | R63: 6.1 | S63: 4.65 | T63: 17.32 | U63: 8.02 | V63: 8.02 | W63: 100 | Y63: 62 | Z63: 2.6 | AA63: 0 | AB63: 0.72291667 | AC63: 0
A64: Anthony Cirelli | C64: 0 | D64: C | E64: 5200 | F64: TB | G64: vs WPG | H64: 0.79166667 | I64: Y | J64: 0.518 | K64: -107.5 | L64: 5.5 | M64: 3.2 | N64: 2.75 | O64: 1 | P64: 2 | Q64: 0.73263889 | R64: 8.5 | S64: 6.6 | T64: 22.77 | U64: 9.57 | V64: 9.57 | W64: 100 | Y64: 61 | Z64: 1.8 | AA64: 0 | AB64: 0.68472222 | AC64: 4.5 | AD64: 0.9
A65: Tony DeAngelo | C65: 0 | D65: D | E65: 4100 | F65: NYI | G65: @ NYR | H65: 0.79166667 | I65: Y | J65: 0.472 | K65: -89.5 | L65: 6 | M65: 3 | N65: 2.82 | O65: 2 | P65: 1 | Q65: 0.76944444 | R65: 7 | S65: 5.89 | T65: 20.8 | U65: 9.02 | V65: 9.02 | W65: 100 | Y65: 58 | Z65: 2.2 | AA65: 0 | AB65: 0.83958333 | AC65: 8.6 | AD65: 2.1
A66: Anthony Duclair | C66: 0 | D66: W | E66: 3900 | F66: NYI | G66: @ NYR | H66: 0.79166667 | I66: Y | J66: 0.472 | K66: -89.5 | L66: 6 | M66: 3 | N66: 2.82 | O66: 2 | P66: 1 | Q66: 0.56388889 | R66: 6.2 | S66: 7.03 | T66: 22.09 | U66: 8.03 | V66: 8.03 | W66: 100 | Y66: 43 | Z66: 2.1 | AA66: 0 | AB66: 0.58194444 | AC66: 0
A67: Anthony Mantha | C67: 0 | D67: W | E67: 3200 | F67: PIT | G67: vs CHI | H67: 0.79166667 | I67: Y | J67: 0.507 | K67: -103 | L67: 6.5 | M67: 3.71 | N67: 3.25 | O67: 3 | P67: 2 | Q67: 0.61666667 | R67: 7.9 | S67: 6.45 | T67: 23.82 | U67: 10.92 | V67: 10.92 | W67: 100 | Y67: 59 | Z67: 3.4 | AA67: 0 | AB67: 0.56041667 | AC67: 26 | AD67: 8.1
A68: Anthony Stolarz | C68: 0 | D68: G | E68: 7800 | F68: TOR | G68: @ SEA | H68: 0.91666667 | I68: N | J68: 0.585 | K68: 71 | L68: 6 | M68: 3 | N68: 3.02 | O68: confirm | Q68: 2.2638889 | R68: 8.6 | S68: 9.33 | T68: 30.25 | U68: 11.59 | V68: 11.59 | W68: 100 | Y68: 46 | Z68: 1.5 | AA68: 0 | AB68: 2.4402778 | AC68: -2.1
A69: Anton Blidh | C69: 0 | D69: W | E69: 2500 | F69: NYR | G69: vs NYI | H69: 0.79166667 | I69: N | J69: 0.528 | K69: 89.5 | L69: 6 | M69: 2.82 | N69: 3 | Q69: 0.30277778 | R69: 3.7 | S69: 4.17 | T69: 0 | U69: 0 | V69: 0 | W69: 100 | Y69: 44 | Z69: 0 | AA69: 0
A70: Anton Forsberg | C70: 0 | D70: G | E70: 7400 | F70: LA | G70: @ BUF | H70: 0.79166667 | I70: N | J70: 0.565 | K70: 77 | L70: 5.5 | M70: 2.75 | N70: 2.87 | O70: unlikely | Q70: 2.3743056 | R70: 11.5 | S70: 7.83 | T70: 0 | U70: 0 | V70: 0 | W70: 100 | Y70: 66 | Z70: 0 | AA70: 0 | AB70: 0 | AC70: 0
A71: Anton Lundell | B71: ! | C71: 0 | D71: C | E71: 4600 | F71: FLA | G71: @ STL | H71: 0.83333333 | I71: Y | J71: 0.487 | K71: -95 | L71: 5.5 | M71: 2.75 | N71: 2.54 | Q71: 0.79027778 | R71: 9.1 | S71: 6.53 | T71: 0 | U71: 0 | V71: 0 | W71: 100 | Y71: 64 | Z71: 0 | AA71: 0
A72: Anze Kopitar | C72: 0 | D72: C | E72: 3700 | F72: LA | G72: @ BUF | H72: 0.79166667 | I72: N | J72: 0.565 | K72: 77 | L72: 5.5 | M72: 2.75 | N72: 2.87 | Q72: 0.77083333 | R72: 6.7 | S72: 5.38 | T72: 0 | U72: 0 | V72: 0 | W72: 100 | Y72: 60 | Z72: 0 | AA72: 0
A73: Arber Xhekaj | C73: 0 | D73: D | E73: 2500 | F73: MTL | G73: vs COL | H73: 0.79166667 | I73: N | J73: 0.551 | K73: 81.5 | L73: 6.5 | M73: 3.17 | N73: 3.25 | O73: 3 | Q73: 0.48472222 | R73: 2.3 | S73: 2.37 | T73: 7.46 | U73: 2.72 | V73: 2.72 | W73: 100 | Y73: 48 | Z73: 1.1 | AA73: 0 | AB73: 0.56805556 | AC73: 0
A74: Arseny Gritsyuk | C74: 0 | D74: W | E74: 3300 | F74: NJ | G74: vs NSH | H74: 0.79166667 | I74: Y | J74: 0.464 | K74: -86.5 | L74: 6 | M74: 3.19 | N74: 3 | O74: 2 | P74: 2 | Q74: 0.62291667 | R74: 6.7 | S74: 6 | T74: 19.62 | U74: 7.62 | V74: 7.62 | W74: 100 | Y74: 55 | Z74: 2.3 | AA74: 0 | AB74: 0.78194444 | AC74: 17.9 | AD74: 5.4
A75: Arshdeep Bains | C75: 0 | D75: W | E75: 2500 | F75: VAN | G75: vs ANA | H75: 0.91666667 | I75: N | J75: 0.512 | K75: 95.5 | L75: 6.5 | M75: 3.01 | N75: 3.25 | Q75: 0.39166667 | R75: 2.4 | S75: 3.25 | T75: 0 | U75: 0 | V75: 0 | W75: 100 | Y75: 32 | Z75: 0 | AA75: 0
A76: Artemi Panarin | C76: 0 | D76: W | E76: 8000 | F76: NYR | G76: vs NYI | H76: 0.79166667 | I76: N | J76: 0.528 | K76: 89.5 | L76: 6 | M76: 2.82 | N76: 3 | Q76: 0.86944444 | R76: 12.6 | S76: 9.58 | T76: 0 | U76: 0 | V76: 0 | W76: 100 | Y76: 62 | Z76: 0 | AA76: 0
A77: Artturi Lehkonen | C77: 0 | D77: W | E77: 5500 | F77: COL | G77: @ MTL | H77: 0.79166667 | I77: Y | J77: 0.449 | K77: -81.5 | L77: 6.5 | M77: 3.25 | N77: 3.17 | O77: 1 | P77: 2 | Q77: 0.8 | R77: 8.9 | S77: 6.34 | T77: 22 | U77: 9.32 | V77: 9.32 | W77: 100 | Y77: 64 | Z77: 1.7 | AA77: 0 | AB77: 0.74652778 | AC77: 7.3 | AD77: 1.3
A78: Arturs Silovs | C78: 0 | D78: G | E78: 8300 | F78: PIT | G78: vs CHI | H78: 0.79166667 | I78: Y | J78: 0.507 | K78: -103 | L78: 6.5 | M78: 3.71 | N78: 3.25 | O78: confirm | Q78: 2.4277778 | R78: 10.3 | S78: 9.32 | T78: 29.35 | U78: 10.71 | V78: 10.71 | W78: 100 | Y78: 55 | Z78: 1.3 | AA78: 0 | AB78: 2.4979167 | AC78: 11.6 | AD78: 1.4
A79: Artyom Levshunov | C79: 0 | D79: D | E79: 3300 | F79: CHI | G79: @ PIT | H79: 0.79166667 | I79: N | J79: 0.493 | K79: 103 | L79: 6.5 | M79: 3.25 | N79: 3.71 | O79: 2 | P79: 1 | Q79: 0.79791667 | R79: 5.6 | S79: 4.34 | T79: 15.44 | U79: 6.76 | V79: 6.76 | W79: 100 | Y79: 61 | Z79: 2 | AA79: 0 | AB79: 0.86527778 | AC79: 1.3 | AD79: 0.4
A80: Arvid Soderblom | C80: 0 | D80: G | E80: 7100 | F80: CHI | G80: @ PIT | H80: 0.79166667 | I80: N | J80: 0.493 | K80: 103 | L80: 6.5 | M80: 3.25 | N80: 3.71 | O80: confirm | Q80: 2.4194444 | R80: 7.3 | S80: 10.82 | T80: 30.55 | U80: 8.91 | V80: 8.91 | W80: 100 | Y80: 26 | Z80: 1.3 | AA80: 0 | AB80: 2.5 | AC80: 8.6 | AD80: 1.2
A81: Auston Matthews | C81: 0 | D81: C | E81: 9700 | F81: TOR | G81: @ SEA | H81: 0.91666667 | I81: N | J81: 0.585 | K81: 71 | L81: 6 | M81: 3 | N81: 3.02 | O81: 1 | P81: 1 | Q81: 0.86597222 | R81: 15.9 | S81: 9.95 | T81: 37.84 | U81: 17.94 | V81: 17.94 | W81: 100 | Y81: 69 | Z81: 1.8 | AA81: 0 | AB81: 0.87361111 | AC81: 6 | AD81: 0.6
A82: Axel Sandin-Pellikka | C82: 0 | D82: D | E82: 2500 | F82: DET | G82: vs WSH | H82: 0.8125 | I82: Y | J82: 0.44 | K82: -78.5 | L82: 6.5 | M82: 3.43 | N82: 3.25 | O82: 2 | P82: 2 | Q82: 0.7 | R82: 5 | S82: 4.56 | T82: 16.15 | U82: 7.03 | V82: 7.03 | W82: 100 | Y82: 54 | Z82: 2.8 | AA82: 0 | AB82: 0.47222222 | AC82: 1.3 | AD82: 0.5
A83: Barclay Goodrow | C83: 0 | D83: W | E83: 2500 | F83: SJ | G83: @ EDM | H83: 0.875 | I83: N | J83: 0.471 | K83: 112.5 | L83: 7 | M83: 3.5 | N83: 4.05 | O83: 4 | Q83: 0.48125 | R83: 3.8 | S83: 5.18 | T83: 16.42 | U83: 6.06 | V83: 6.06 | W83: 100 | Y83: 32 | Z83: 2.4 | AA83: 0 | AB83: 0.48402778 | AC83: 1.3 | AD83: 0.5
A84: Barrett Hayton | C84: 0 | D84: C | E84: 3300 | F84: UTA | G84: @ CAR | H84: 0.79166667 | I84: N | J84: 0.494 | K84: 102.5 | L84: 6 | M84: 3 | N84: 3.44 | O84: 2 | P84: 1 | Q84: 0.63611111 | R84: 5.8 | S84: 5.07 | T84: 17.56 | U84: 7.42 | V84: 7.42 | W84: 100 | Y84: 56 | Z84: 2.2 | AA84: 0 | AB84: 0.58402778 | AC84: 9.5 | AD84: 2.9
A85: Beck Malenstyn | C85: 0 | D85: W | E85: 2500 | F85: BUF | G85: vs LA | H85: 0.79166667 | I85: Y | J85: 0.435 | K85: -77 | L85: 5.5 | M85: 2.87 | N85: 2.75 | O85: 4 | Q85: 0.46875 | R85: 3.8 | S85: 3.79 | T85: 11.09 | U85: 3.51 | V85: 3.51 | W85: 100 | Y85: 50 | Z85: 1.4 | AA85: 0 | AB85: 0.51875 | AC85: 1.3 | AD85: 0.5
A86: Beckett Sennecke | C86: 0 | D86: W | E86: 5700 | F86: ANA | G86: @ VAN | H86: 0.91666667 | I86: Y | J86: 0.488 | K86: -95.5 | L86: 6.5 | M86: 3.25 | N86: 3.01 | O86: 1 | P86: 1 | Q86: 0.71527778 | R86: 9.5 | S86: 8.28 | T86: 29.66 | U86: 13.1 | V86: 13.1 | W86: 100 | Y86: 56 | Z86: 2.3 | AA86: 0 | AB86: 0.875 | AC86: 4.5 | AD86: 0.8
A87: Ben Chiarot | C87: 0 | D87: D | E87: 3100 | F87: DET | G87: vs WSH | H87: 0.8125 | I87: Y | J87: 0.44 | K87: -78.5 | L87: 6.5 | M87: 3.43 | N87: 3.25 | O87: 2 | Q87: 0.87638889 | R87: 7.1 | S87: 5.04 | T87: 18.45 | U87: 8.37 | V87: 8.37 | W87: 100 | Y87: 65 | Z87: 2.7 | AA87: 0 | AB87: 0.86111111 | AC87: 12.8 | AD87: 4.1
A88: Ben Hutton | C88: 0 | D88: D | E88: 2500 | F88: VGK | G88: vs DAL | H88: 0.91666667 | I88: Y | J88: 0.465 | K88: -87 | L88: 6 | M88: 3.14 | N88: 3 | O88: 3 | Q88: 0.61666667 | R88: 5.6 | S88: 4.77 | T88: 15.77 | U88: 6.23 | V88: 6.23 | W88: 100 | Y88: 57 | Z88: 2.5 | AA88: 0 | AB88: 0.65972222 | AC88: 1.5 | AD88: 0.6
A89: Ben Jones | C89: 0 | D89: W | E89: 2500 | F89: MIN | G89: vs CGY | H89: 0.83333333 | I89: Y | J89: 0.513 | K89: -105.5 | L89: 6 | M89: 3.46 | N89: 3 | Q89: 0.35833333 | R89: 2.6 | S89: 2.72 | T89: 0 | U89: 0 | V89: 0 | W89: 100 | Y89: 48 | Z89: 0 | AA89: 0
A90: Ben Kindel | C90: 0 | D90: W | E90: 4000 | F90: PIT | G90: vs CHI | H90: 0.79166667 | I90: Y | J90: 0.507 | K90: -103 | L90: 6.5 | M90: 3.71 | N90: 3.25 | O90: 3 | P90: 2 | Q90: 0.64097222 | R90: 7.8 | S90: 7.14 | T90: 25.36 | U90: 11.08 | V90: 11.08 | W90: 100 | Y90: 54 | Z90: 2.8 | AA90: 0 | AB90: 0.52430556 | AC90: 16.3 | AD90: 4.1
A91: Ben Meyers | C91: 0 | D91: C | E91: 2500 | F91: SEA | G91: vs TOR | H91: 0.91666667 | I91: Y | J91: 0.415 | K91: -71 | L91: 6 | M91: 3.02 | N91: 3 | Q91: 0.48472222 | R91: 4.7 | S91: 5.53 | T91: 0 | U91: 0 | V91: 0 | W91: 100 | Y91: 41 | Z91: 0 | AA91: 0
A92: Berkly Catton | C92: 0 | D92: W | E92: 3300 | F92: SEA | G92: vs TOR | H92: 0.91666667 | I92: Y | J92: 0.415 | K92: -71 | L92: 6 | M92: 3.02 | N92: 3 | O92: 2 | Q92: 0.52916667 | R92: 4.2 | S92: 4.31 | T92: 13.66 | U92: 5.04 | V92: 5.04 | W92: 100 | Y92: 49 | Z92: 1.5 | AA92: 0 | AB92: 0.13333333 | AC92: 0
A93: Blake Coleman | C93: 0 | D93: W | E93: 3900 | F93: CGY | G93: @ MIN | H93: 0.83333333 | I93: N | J93: 0.487 | K93: 105.5 | L93: 6 | M93: 3 | N93: 3.46 | Q93: 0.70625 | R93: 8.1 | S93: 6.14 | T93: 0 | U93: 0 | V93: 0 | W93: 100 | Y93: 62 | Z93: 0 | AA93: 0
A94: Blake Lizotte | C94: 0 | D94: C | E94: 2500 | F94: PIT | G94: vs CHI | H94: 0.79166667 | I94: Y | J94: 0.507 | K94: -103 | L94: 6.5 | M94: 3.71 | N94: 3.25 | O94: 4 | Q94: 0.57013889 | R94: 4.2 | S94: 4.54 | T94: 15.67 | U94: 6.59 | V94: 6.59 | W94: 100 | Y94: 46 | Z94: 2.6 | AA94: 0 | AB94: 0.54861111 | AC94: 12.6 | AD94: 5
A95: Bo Horvat | C95: 0 | D95: C | E95: 7900 | F95: NYI | G95: @ NYR | H95: 0.79166667 | I95: Y | J95: 0.472 | K95: -89.5 | L95: 6 | M95: 3 | N95: 2.82 | O95: 1 | P95: 2 | Q95: 0.84375 | R95: 12 | S95: 7.54 | T95: 28.33 | U95: 13.25 | V95: 13.25 | W95: 100 | Y95: 69 | Z95: 1.7 | AA95: 0 | AB95: 0.82986111 | AC95: 10.6 | AD95: 1.3
A96: Bobby Brink | C96: 0 | D96: W | E96: 3800 | F96: PHI | G96: @ BOS | H96: 0.79166667 | I96: N | J96: 0.519 | K96: 92.5 | L96: 6.5 | M96: 3.25 | N96: 3.62 | O96: 3 | P96: 1 | Q96: 0.64305556 | R96: 6.6 | S96: 5.95 | T96: 19.88 | U96: 7.98 | V96: 7.98 | W96: 100 | Y96: 55 | Z96: 2.1 | AA96: 0 | AB96: 0.67430556 | AC96: 1.3 | AD96: 0.3
A97: Bobby McMann | C97: 0 | D97: W | E97: 4500 | F97: TOR | G97: @ SEA | H97: 0.91666667 | I97: N | J97: 0.585 | K97: 71 | L97: 6 | M97: 3 | N97: 3.02 | O97: 1 | P97: 2 | Q97: 0.63472222 | R97: 7.7 | S97: 6.68 | T97: 23.45 | U97: 10.09 | V97: 10.09 | W97: 100 | Y97: 57 | Z97: 2.2 | AA97: 0 | AB97: 0.70555556 | AC97: 4.5 | AD97: 1
A98: Bogdan Trineyev | C98: 0 | D98: W | E98: 2500 | F98: WSH | G98: @ DET | H98: 0.8125 | I98: N | J98: 0.56 | K98: 78.5 | L98: 6.5 | M98: 3.25 | N98: 3.43 | Q98: 0.43819444 | R98: 2.1 | S98: 0.75 | T98: 0 | U98: 0 | V98: 0 | W98: 100 | Y98: 0 | Z98: 0 | AA98: 0
A99: Boko Imama | C99: 0 | D99: W | E99: 2500 | F99: PIT | G99: vs CHI | H99: 0.79166667 | I99: Y | J99: 0.507 | K99: -103 | L99: 6.5 | M99: 3.71 | N99: 3.25 | T99: 0 | U99: 0 | V99: 0 | W99: 100 | Y99: 0 | Z99: 0 | AA99: 0
A100: Boris Katchouk | C100: 0 | D100: W | E100: 2500 | F100: TB | G100: vs WPG | H100: 0.79166667 | I100: Y | J100: 0.518 | K100: -107.5 | L100: 5.5 | M100: 3.2 | N100: 2.75 | Q100: 0.59861111 | R100: 1.4 | S100: 1.41 | T100: 0 | U100: 0 | V100: 0 | W100: 100 | Y100: 50 | Z100: 0 | AA100: 0
...
